hardware/simulation/74hc165.vhdl
library IEEE;
use IEEE.std_logic_1164.all;

entity T74HCT165 is
port (
    nPL                 : IN  std_logic;
    nCE                : IN  std_logic;
    CP                  : IN  std_logic;
    DS                  : IN  std_logic;
    D                    : IN  std_logic_vector(7 downto 0);
    Q7                  : OUT std_logic;
    nQ7                : OUT std_logic
);
end T74HCT165;

architecture behave_T74HCT165 of T74HCT165 is
signal  Qs            : std_logic_vector(7 downto 0) ;

begin
HCT165 : process(nPL, CP, D)
begin
    if(nPL = '0') then
        Qs <= D;
    elsif(CP'event and CP = '1') then
        if(nCE = '0') then
            Qs <= Qs(6 downto 0) & DS;    -- or  Qs <= shl(Qs, '1') & DS;
        end if;
    end if;
end process;
    Q7 <= Qs(7);
    nQ7 <= not(Qs(7));
end behave_T74HCT165;

hardware/simulation/tile.vhdl
library ieee;
use ieee.std_logic_1164.all;
use IEEE.NUMERIC_STD.ALL;

entity tile is
  port (
    buttons : in std_logic_vector(11 downto 0) := (others => 'L');

    T_W : in std_logic := 'Z';
    T_endcol : in std_logic := 'Z';
    T_first : out std_logic := '0';
    T_latch : out std_logic;
    T_clk : out std_logic;
    T_data : in std_logic := 'Z';

    B_W : out std_logic;
    B_endcol : out std_logic := '0';
    B_first : in std_logic := 'Z';
    B_latch : in std_logic := 'Z';
    B_clk : in std_logic := 'Z';
    B_data : out std_logic;

    L_endrow : in std_logic := 'Z';
    L_latch : out std_logic;
    L_clk : out std_logic;
    L_data : in std_logic := 'Z';

    R_endrow : out std_logic := '0';
    R_latch : in std_logic := 'Z';
    R_clk : in std_logic := 'Z';
    R_data : out std_logic
  );
end tile;

architecture rtl of tile is

signal latch, clock, data : std_logic; -- main signals
signal nlatch : std_logic;

signal ds_bridge : std_logic; -- serial output of SR2 into SR1
signal ds_input : std_logic; -- serial input from the neighbouring tiles

signal w_state : std_logic; -- state of the 3-state buffers (W: chain from top or left)

signal count_reg : unsigned(5 downto 0) := (others => '0'); -- counter
signal count : std_logic_vector(5 downto 0);

signal sr2_inputs : std_logic_vector(7 downto 0); -- helper signal
signal ffinput : std_logic;

signal T_W_p, T_endcol_p, T_data_p, B_first_p, B_latch_p, B_clk_p, L_endrow_p, L_data_p, R_latch_p, R_clk_p : std_logic;

begin

  -- input pullups / pulldowns
  T_W_p       <= 'H';
  T_endcol_p  <= 'H';
  T_data_p    <= 'L';
  B_first_p   <= 'H';
  B_latch_p   <= 'L';
  B_clk_p     <= 'H';
  L_endrow_p  <= 'H';
  L_data_p    <= 'L';
  R_latch_p   <= 'L';
  R_clk_p     <= 'H';

  T_W_p       <=   T_W;
  T_endcol_p  <=   T_endcol;
  T_data_p    <=   T_data;
  B_first_p   <=   B_first;
  B_latch_p   <=   B_latch;
  B_clk_p     <=   B_clk;
  L_endrow_p  <=   L_endrow;
  L_data_p    <=   L_data;
  R_latch_p   <=   R_latch;
  R_clk_p     <=   R_clk;


  -- inputs wiring
  clock <= R_clk_p;
  clock <= B_clk_p;

  w_state <= T_W_p and B_first_p;

  latch <= R_latch_p or B_latch_p;  -- the latch behaves like a reset, so the two sources are ORed
  ds_input <= T_data_p when to_x01(w_state) = '0' else L_data_p;


  -- outputs wiring
  R_data <= data;
  B_data <= data;

  T_latch <= latch;
  L_latch <= latch;

  T_clk <= clock when to_x01(w_state) = '0' else 'Z';
  L_clk <= clock when to_x01(w_state) = '1' else 'Z';



  nlatch <= not latch;



  -- sr LSB
  sr1 : entity work.T74HCT165
    port map(
      nPL => nlatch,
      nCE => '0',
      CP => clock,
      DS => ds_bridge,
      D => buttons(11 downto 4),
      Q7 => data,
      nQ7 => open
    );

  sr2_inputs <= buttons(3 downto 0) & "11" & to_x01(L_endrow_p) & to_x01(T_endcol_p);

  -- sr MSB
  sr2 : entity work.T74HCT165
    port map(
      nPL => nlatch,
      nCE => '0',
      CP => clock,
      DS => ds_input,
      D => sr2_inputs,
      Q7 => ds_bridge,
      nQ7 => open
    );



  process(clock, latch)
  begin
    if latch = '1' then
      count_reg <= (others => '0');
    elsif rising_edge(clock) then
      count_reg <= count_reg + 1;
    end if;
  end process;

  count <= std_logic_vector(count_reg);
  ffinput <= count(3) and count(2) and count(1) and count(0) and data;

  process(clock, latch)
  begin
    if latch = '1' then
      B_W <= '0';
    elsif rising_edge(clock) then
      if ffinput = '1' then
        B_W <= '1';
      end if;
    end if;
  end process;


end rtl;

hardware/simulation/tile_tb_2.vhdl
library ieee;
use ieee.std_logic_1164.all;
use ieee.numeric_std.all;

entity tile_tb_2 is
end tile_tb_2;

architecture sim of tile_tb_2 is

  signal buttons11    : std_logic_vector(11 downto 0);
  signal buttons21    : std_logic_vector(11 downto 0);
  signal buttons12    : std_logic_vector(11 downto 0);
  signal buttons22    : std_logic_vector(11 downto 0);
  signal buttons32    : std_logic_vector(11 downto 0);

  signal latch, clk, data : std_logic;

  constant CLK_PERIOD : time := 10 ns;

  signal clk_en : std_logic := '0';

  -- sengali di collegamento fra 11 e 21
  signal W_11_21, endcol_11_21, first_11_21, latch_11_21, clock_11_21, data_11_21 : std_logic;
  -- sengali di collegamento fra 11 e 12
  signal endrow_11_12, latch_11_12, clock_11_12, data_11_12 : std_logic;
  -- sengali di collegamento fra 12 e 22
  signal W_12_22, endcol_12_22, first_12_22, latch_12_22, clock_12_22, data_12_22 : std_logic;
  -- sengali di collegamento fra 22 e 32
  signal W_22_32, endcol_22_32, first_22_32, latch_22_32, clock_22_32, data_22_32 : std_logic;
  -- sengali di collegamento fra 21 e 22
  signal endrow_21_22, latch_21_22, clock_21_22, data_21_22 : std_logic;



  signal sr_controllo : std_logic_vector(95 downto 0) := (others => '0');

begin

    -- Istanza del tuo modulo
    uut11: entity work.tile
        port map (
            buttons => buttons11,
            T_W => W_11_21,
            T_endcol => endcol_11_21,
            T_first => first_11_21,
            T_latch => latch_11_21,
            T_clk => clock_11_21,
            T_data => data_11_21,
            B_W => open,
            B_endcol => open,
            B_data => open,
            L_endrow => endrow_11_12,
            L_latch => latch_11_12,
            L_clk => clock_11_12,
            L_data => data_11_12,
            R_endrow => open,
            R_latch => latch,
            R_clk => clk,
            R_data => data
        );

    uut21: entity work.tile
        port map (
            buttons => buttons21,
            T_first => open,
            T_latch => open,
            T_clk => open,
            B_W => W_11_21,
            B_endcol => endcol_11_21,
            B_first => first_11_21,
            B_latch => latch_11_21,
            B_clk => clock_11_21,
            B_data => data_11_21,
            L_endrow => endrow_21_22,
            L_latch => latch_21_22,
            L_clk => clock_21_22,
            L_data => data_21_22,
            R_endrow => open,
            R_data => open
        );

    uut12: entity work.tile
        port map (
            buttons => buttons12,
            T_W => W_12_22,
            T_endcol => endcol_12_22,
            T_first => first_12_22,
            T_latch => latch_12_22,
            T_clk => clock_12_22,
            T_data => data_12_22,
            B_W => open,
            B_endcol => open,
            B_data => open,
            L_latch => open,
            L_clk => open,
            R_endrow => endrow_11_12,
            R_data => data_11_12,
            R_clk => clock_11_12,
            R_latch => latch_11_12
        );

    uut22: entity work.tile
        port map (
            buttons => buttons22,
            T_W => W_22_32,
            T_endcol => endcol_22_32,
            T_first => first_22_32,
            T_latch => latch_22_32,
            T_clk => clock_22_32,
            T_data => data_22_32,
            B_W => W_12_22,
            B_endcol => endcol_12_22,
            B_first => first_12_22,
            B_latch => latch_12_22,
            B_clk => clock_12_22,
            B_data => data_12_22,
            L_latch => open,
            L_clk => open,
            R_endrow => endrow_21_22,
            R_data => data_21_22,
            R_clk => clock_21_22,
            R_latch => latch_21_22
        );

    uut32: entity work.tile
        port map (
            buttons => buttons32,
            T_first => open,
            T_latch => open,
            T_clk => open,
            B_W => W_22_32,
            B_endcol => endcol_22_32,
            B_first => first_22_32,
            B_latch => latch_22_32,
            B_clk => clock_22_32,
            B_data => data_22_32,
            L_latch => open,
            L_clk => open,
            R_endrow => open,
            R_data => open
        );



    -- Generatore di Clock (sulla linea R_clk)
    clk_process : process  -- RIMOSSO (clk_en)
    begin
        while true loop
            if clk_en = '1' then
                clk <= '0';
                wait for CLK_PERIOD/2;
                clk <= '1';
                wait for CLK_PERIOD/2;
            else
                clk <= '0';
                -- Fondamentale: se il clock è disabilitato, dobbiamo
                -- aspettare che clk_en cambi, altrimenti il loop gira
                -- all'infinito nello stesso istante di tempo (hang).
                wait until clk_en = '1';
            end if;
        end loop;
        wait; -- Ferma tutto dopo 500 ns
    end process;



    capture_data: process(clk)
    begin
        if rising_edge(clk) then
            if latch = '0' then
                -- shift a sinistra: il nuovo bit entra dalla posizione 0
                sr_controllo <= sr_controllo(94 downto 0) & data;
            end if;
        end if;
    end process;



    -- Stimolo principale
    stim_proc: process
    begin

        buttons11 <= x"B44";
        buttons21 <= x"C23";
        buttons12 <= x"34D";
        buttons22 <= x"E11";
        buttons32 <= x"F55";

        latch <= '1';  -- stato di reset
        wait for 20 ns;
        latch <= '0'; -- shifting
        wait for 20 ns;

        clk_en <= '1';
        wait for CLK_PERIOD * 95;
        clk_en <= '0';

        wait for 40 ns;




        buttons11 <= x"DF3";
        buttons21 <= x"A31";
        buttons12 <= x"000";
        buttons22 <= x"FFF";
        buttons32 <= x"A34";

        latch <= '1';  -- stato di reset
        wait for 20 ns;
        latch <= '0'; -- shifting
        wait for 20 ns;

        clk_en <= '1';
        wait for CLK_PERIOD * 95;
        clk_en <= '0';

        wait for 40 ns;


        --wait for CLK_PERIOD * 2;
        wait;
    end process;

end sim;

hardware/simulation/tile.vcd
$date
  Fri Jan  9 16:25:37 2026
$end
$version
  GHDL v0
$end
$timescale
  1 fs
$end
$scope module standard $end
$upscope $end
$scope module std_logic_1164 $end
$upscope $end
$scope module numeric_std $end
$upscope $end
$scope module tile_tb_2 $end
$var reg 12 ! buttons11[11:0] $end
$var reg 12 " buttons21[11:0] $end
$var reg 12 # buttons12[11:0] $end
$var reg 12 $ buttons22[11:0] $end
$var reg 12 % buttons32[11:0] $end
$var reg 1 & latch $end
$var reg 1 ' clk $end
$var reg 1 ( data $end
$var reg 1 ) clk_en $end
$var reg 1 * w_11_21 $end
$var reg 1 + endcol_11_21 $end
$var reg 1 , first_11_21 $end
$var reg 1 - latch_11_21 $end
$var reg 1 . clock_11_21 $end
$var reg 1 / data_11_21 $end
$var reg 1 0 endrow_11_12 $end
$var reg 1 1 latch_11_12 $end
$var reg 1 2 clock_11_12 $end
$var reg 1 3 data_11_12 $end
$var reg 1 4 w_12_22 $end
$var reg 1 5 endcol_12_22 $end
$var reg 1 6 first_12_22 $end
$var reg 1 7 latch_12_22 $end
$var reg 1 8 clock_12_22 $end
$var reg 1 9 data_12_22 $end
$var reg 1 : w_22_32 $end
$var reg 1 ; endcol_22_32 $end
$var reg 1 < first_22_32 $end
$var reg 1 = latch_22_32 $end
$var reg 1 > clock_22_32 $end
$var reg 1 ? data_22_32 $end
$var reg 1 @ endrow_21_22 $end
$var reg 1 A latch_21_22 $end
$var reg 1 B clock_21_22 $end
$var reg 1 C data_21_22 $end
$var reg 96 D sr_controllo[95:0] $end
$scope module uut11 $end
$var reg 12 E buttons[11:0] $end
$var reg 1 F t_w $end
$var reg 1 G t_endcol $end
$var reg 1 H t_first $end
$var reg 1 I t_latch $end
$var reg 1 J t_clk $end
$var reg 1 K t_data $end
$var reg 1 L b_w $end
$var reg 1 M b_endcol $end
$var reg 1 N b_first $end
$var reg 1 O b_latch $end
$var reg 1 P b_clk $end
$var reg 1 Q b_data $end
$var reg 1 R l_endrow $end
$var reg 1 S l_latch $end
$var reg 1 T l_clk $end
$var reg 1 U l_data $end
$var reg 1 V r_endrow $end
$var reg 1 W r_latch $end
$var reg 1 X r_clk $end
$var reg 1 Y r_data $end
$var reg 1 Z latch $end
$var reg 1 [ clock $end
$var reg 1 \ data $end
$var reg 1 ] nlatch $end
$var reg 1 ^ ds_bridge $end
$var reg 1 _ ds_input $end
$var reg 1 ` w_state $end
$var reg 6 a count_reg[5:0] $end
$var reg 6 b count[5:0] $end
$var reg 8 c sr2_inputs[7:0] $end
$var reg 1 d ffinput $end
$var reg 1 e t_w_p $end
$var reg 1 f t_endcol_p $end
$var reg 1 g t_data_p $end
$var reg 1 h b_first_p $end
$var reg 1 i b_latch_p $end
$var reg 1 j b_clk_p $end
$var reg 1 k l_endrow_p $end
$var reg 1 l l_data_p $end
$var reg 1 m r_latch_p $end
$var reg 1 n r_clk_p $end
$scope module sr1 $end
$var reg 1 o npl $end
$var reg 1 p nce $end
$var reg 1 q cp $end
$var reg 1 r ds $end
$var reg 8 s d[7:0] $end
$var reg 1 t q7 $end
$var reg 1 u nq7 $end
$var reg 8 v qs[7:0] $end
$upscope $end
$scope module sr2 $end
$var reg 1 w npl $end
$var reg 1 x nce $end
$var reg 1 y cp $end
$var reg 1 z ds $end
$var reg 8 { d[7:0] $end
$var reg 1 | q7 $end
$var reg 1 } nq7 $end
$var reg 8 !" qs[7:0] $end
$upscope $end
$upscope $end
$scope module uut21 $end
$var reg 12 "" buttons[11:0] $end
$var reg 1 #" t_w $end
$var reg 1 $" t_endcol $end
$var reg 1 %" t_first $end
$var reg 1 &" t_latch $end
$var reg 1 '" t_clk $end
$var reg 1 (" t_data $end
$var reg 1 )" b_w $end
$var reg 1 *" b_endcol $end
$var reg 1 +" b_first $end
$var reg 1 ," b_latch $end
$var reg 1 -" b_clk $end
$var reg 1 ." b_data $end
$var reg 1 /" l_endrow $end
$var reg 1 0" l_latch $end
$var reg 1 1" l_clk $end
$var reg 1 2" l_data $end
$var reg 1 3" r_endrow $end
$var reg 1 4" r_latch $end
$var reg 1 5" r_clk $end
$var reg 1 6" r_data $end
$var reg 1 7" latch $end
$var reg 1 8" clock $end
$var reg 1 9" data $end
$var reg 1 :" nlatch $end
$var reg 1 ;" ds_bridge $end
$var reg 1 <" ds_input $end
$var reg 1 =" w_state $end
$var reg 6 >" count_reg[5:0] $end
$var reg 6 ?" count[5:0] $end
$var reg 8 @" sr2_inputs[7:0] $end
$var reg 1 A" ffinput $end
$var reg 1 B" t_w_p $end
$var reg 1 C" t_endcol_p $end
$var reg 1 D" t_data_p $end
$var reg 1 E" b_first_p $end
$var reg 1 F" b_latch_p $end
$var reg 1 G" b_clk_p $end
$var reg 1 H" l_endrow_p $end
$var reg 1 I" l_data_p $end
$var reg 1 J" r_latch_p $end
$var reg 1 K" r_clk_p $end
$scope module sr1 $end
$var reg 1 L" npl $end
$var reg 1 M" nce $end
$var reg 1 N" cp $end
$var reg 1 O" ds $end
$var reg 8 P" d[7:0] $end
$var reg 1 Q" q7 $end
$var reg 1 R" nq7 $end
$var reg 8 S" qs[7:0] $end
$upscope $end
$scope module sr2 $end
$var reg 1 T" npl $end
$var reg 1 U" nce $end
$var reg 1 V" cp $end
$var reg 1 W" ds $end
$var reg 8 X" d[7:0] $end
$var reg 1 Y" q7 $end
$var reg 1 Z" nq7 $end
$var reg 8 [" qs[7:0] $end
$upscope $end
$upscope $end
$scope module uut12 $end
$var reg 12 \" buttons[11:0] $end
$var reg 1 ]" t_w $end
$var reg 1 ^" t_endcol $end
$var reg 1 _" t_first $end
$var reg 1 `" t_latch $end
$var reg 1 a" t_clk $end
$var reg 1 b" t_data $end
$var reg 1 c" b_w $end
$var reg 1 d" b_endcol $end
$var reg 1 e" b_first $end
$var reg 1 f" b_latch $end
$var reg 1 g" b_clk $end
$var reg 1 h" b_data $end
$var reg 1 i" l_endrow $end
$var reg 1 j" l_latch $end
$var reg 1 k" l_clk $end
$var reg 1 l" l_data $end
$var reg 1 m" r_endrow $end
$var reg 1 n" r_latch $end
$var reg 1 o" r_clk $end
$var reg 1 p" r_data $end
$var reg 1 q" latch $end
$var reg 1 r" clock $end
$var reg 1 s" data $end
$var reg 1 t" nlatch $end
$var reg 1 u" ds_bridge $end
$var reg 1 v" ds_input $end
$var reg 1 w" w_state $end
$var reg 6 x" count_reg[5:0] $end
$var reg 6 y" count[5:0] $end
$var reg 8 z" sr2_inputs[7:0] $end
$var reg 1 {" ffinput $end
$var reg 1 |" t_w_p $end
$var reg 1 }" t_endcol_p $end
$var reg 1 !# t_data_p $end
$var reg 1 "# b_first_p $end
$var reg 1 ## b_latch_p $end
$var reg 1 $# b_clk_p $end
$var reg 1 %# l_endrow_p $end
$var reg 1 &# l_data_p $end
$var reg 1 '# r_latch_p $end
$var reg 1 (# r_clk_p $end
$scope module sr1 $end
$var reg 1 )# npl $end
$var reg 1 *# nce $end
$var reg 1 +# cp $end
$var reg 1 ,# ds $end
$var reg 8 -# d[7:0] $end
$var reg 1 .# q7 $end
$var reg 1 /# nq7 $end
$var reg 8 0# qs[7:0] $end
$upscope $end
$scope module sr2 $end
$var reg 1 1# npl $end
$var reg 1 2# nce $end
$var reg 1 3# cp $end
$var reg 1 4# ds $end
$var reg 8 5# d[7:0] $end
$var reg 1 6# q7 $end
$var reg 1 7# nq7 $end
$var reg 8 8# qs[7:0] $end
$upscope $end
$upscope $end
$scope module uut22 $end
$var reg 12 9# buttons[11:0] $end
$var reg 1 :# t_w $end
$var reg 1 ;# t_endcol $end
$var reg 1 <# t_first $end
$var reg 1 =# t_latch $end
$var reg 1 ># t_clk $end
$var reg 1 ?# t_data $end
$var reg 1 @# b_w $end
$var reg 1 A# b_endcol $end
$var reg 1 B# b_first $end
$var reg 1 C# b_latch $end
$var reg 1 D# b_clk $end
$var reg 1 E# b_data $end
$var reg 1 F# l_endrow $end
$var reg 1 G# l_latch $end
$var reg 1 H# l_clk $end
$var reg 1 I# l_data $end
$var reg 1 J# r_endrow $end
$var reg 1 K# r_latch $end
$var reg 1 L# r_clk $end
$var reg 1 M# r_data $end
$var reg 1 N# latch $end
$var reg 1 O# clock $end
$var reg 1 P# data $end
$var reg 1 Q# nlatch $end
$var reg 1 R# ds_bridge $end
$var reg 1 S# ds_input $end
$var reg 1 T# w_state $end
$var reg 6 U# count_reg[5:0] $end
$var reg 6 V# count[5:0] $end
$var reg 8 W# sr2_inputs[7:0] $end
$var reg 1 X# ffinput $end
$var reg 1 Y# t_w_p $end
$var reg 1 Z# t_endcol_p $end
$var reg 1 [# t_data_p $end
$var reg 1 \# b_first_p $end
$var reg 1 ]# b_latch_p $end
$var reg 1 ^# b_clk_p $end
$var reg 1 _# l_endrow_p $end
$var reg 1 `# l_data_p $end
$var reg 1 a# r_latch_p $end
$var reg 1 b# r_clk_p $end
$scope module sr1 $end
$var reg 1 c# npl $end
$var reg 1 d# nce $end
$var reg 1 e# cp $end
$var reg 1 f# ds $end
$var reg 8 g# d[7:0] $end
$var reg 1 h# q7 $end
$var reg 1 i# nq7 $end
$var reg 8 j# qs[7:0] $end
$upscope $end
$scope module sr2 $end
$var reg 1 k# npl $end
$var reg 1 l# nce $end
$var reg 1 m# cp $end
$var reg 1 n# ds $end
$var reg 8 o# d[7:0] $end
$var reg 1 p# q7 $end
$var reg 1 q# nq7 $end
$var reg 8 r# qs[7:0] $end
$upscope $end
$upscope $end
$scope module uut32 $end
$var reg 12 s# buttons[11:0] $end
$var reg 1 t# t_w $end
$var reg 1 u# t_endcol $end
$var reg 1 v# t_first $end
$var reg 1 w# t_latch $end
$var reg 1 x# t_clk $end
$var reg 1 y# t_data $end
$var reg 1 z# b_w $end
$var reg 1 {# b_endcol $end
$var reg 1 |# b_first $end
$var reg 1 }# b_latch $end
$var reg 1 !$ b_clk $end
$var reg 1 "$ b_data $end
$var reg 1 #$ l_endrow $end
$var reg 1 $$ l_latch $end
$var reg 1 %$ l_clk $end
$var reg 1 &$ l_data $end
$var reg 1 '$ r_endrow $end
$var reg 1 ($ r_latch $end
$var reg 1 )$ r_clk $end
$var reg 1 *$ r_data $end
$var reg 1 +$ latch $end
$var reg 1 ,$ clock $end
$var reg 1 -$ data $end
$var reg 1 .$ nlatch $end
$var reg 1 /$ ds_bridge $end
$var reg 1 0$ ds_input $end
$var reg 1 1$ w_state $end
$var reg 6 2$ count_reg[5:0] $end
$var reg 6 3$ count[5:0] $end
$var reg 8 4$ sr2_inputs[7:0] $end
$var reg 1 5$ ffinput $end
$var reg 1 6$ t_w_p $end
$var reg 1 7$ t_endcol_p $end
$var reg 1 8$ t_data_p $end
$var reg 1 9$ b_first_p $end
$var reg 1 :$ b_latch_p $end
$var reg 1 ;$ b_clk_p $end
$var reg 1 <$ l_endrow_p $end
$var reg 1 =$ l_data_p $end
$var reg 1 >$ r_latch_p $end
$var reg 1 ?$ r_clk_p $end
$scope module sr1 $end
$var reg 1 @$ npl $end
$var reg 1 A$ nce $end
$var reg 1 B$ cp $end
$var reg 1 C$ ds $end
$var reg 8 D$ d[7:0] $end
$var reg 1 E$ q7 $end
$var reg 1 F$ nq7 $end
$var reg 8 G$ qs[7:0] $end
$upscope $end
$scope module sr2 $end
$var reg 1 H$ npl $end
$var reg 1 I$ nce $end
$var reg 1 J$ cp $end
$var reg 1 K$ ds $end
$var reg 8 L$ d[7:0] $end
$var reg 1 M$ q7 $end
$var reg 1 N$ nq7 $end
$var reg 8 O$ qs[7:0] $end
$upscope $end
$upscope $end
$upscope $end
$enddefinitions $end
#0
b101101000100 !
b110000100011 "
b001101001101 #
b111000010001 $
b111101010101 %
1&
0'
1(
0)
0*
0+
0,
1-
0.
1/
00
11
Z2
03
04
05
06
17
H8
19
0:
0;
0<
1=
H>
1?
0@
1A
ZB
1C
b000000000000000000000000000000000000000000000000000000000000000000000000000000000000000000000000 D
b101101000100 E
0F
0G
0H
1I
0J
1K
0L
0M
ZN
ZO
ZP
1Q
0R
1S
ZT
0U
0V
1W
0X
1Y
1Z
0[
1\
0]
0^
1_
0`
b000000 a
b000000 b
b01001100 c
0d
0e
0f
1g
Hh
Li
Hj
0k
0l
1m
0n
0o
0p
0q
0r
b10110100 s
1t
0u
b10110100 v
0w
0x
0y
1z
b01001100 {
0|
1}
b01001100 !"
b110000100011 ""
Z#"
Z$"
0%"
1&"
0'"
Z("
0)"
0*"
0+"
1,"
0-"
1."
0/"
10"
Z1"
12"
03"
Z4"
Z5"
16"
17"
08"
19"
0:"
0;"
L<"
0="
b000000 >"
b000000 ?"
b00111101 @"
0A"
HB"
HC"
LD"
0E"
1F"
0G"
0H"
1I"
LJ"
HK"
0L"
0M"
0N"
0O"
b11000010 P"
1Q"
0R"
b11000010 S"
0T"
0U"
0V"
LW"
b00111101 X"
0Y"
1Z"
b00111101 ["
b001101001101 \"
0]"
0^"
0_"
1`"
Ha"
1b"
0c"
0d"
Ze"
Zf"
Zg"
0h"
Zi"
1j"
Zk"
Zl"
0m"
1n"
Zo"
0p"
1q"
Hr"
0s"
0t"
1u"
1v"
0w"
b000000 x"
b000000 y"
b11011110 z"
0{"
0|"
0}"
1!#
H"#
L##
H$#
H%#
L&#
1'#
H(#
0)#
0*#
H+#
1,#
b00110100 -#
0.#
1/#
b00110100 0#
01#
02#
H3#
14#
b11011110 5#
16#
07#
b11011110 8#
b111000010001 9#
0:#
0;#
0<#
1=#
H>#
1?#
0@#
0A#
0B#
1C#
HD#
1E#
ZF#
1G#
ZH#
ZI#
0J#
1K#
ZL#
1M#
1N#
HO#
1P#
0Q#
0R#
1S#
0T#
b000000 U#
b000000 V#
b00011110 W#
0X#
0Y#
0Z#
1[#
0\#
1]#
H^#
H_#
L`#
1a#
Hb#
0c#
0d#
He#
0f#
b11100001 g#
1h#
0i#
b11100001 j#
0k#
0l#
Hm#
1n#
b00011110 o#
0p#
1q#
b00011110 r#
b111101010101 s#
Zt#
Zu#
0v#
1w#
Hx#
Zy#
0z#
0{#
0|#
1}#
H!$
1"$
Z#$
1$$
Z%$
Z&$
0'$
Z($
Z)$
1*$
1+$
H,$
1-$
0.$
0/$
L0$
01$
b000000 2$
b000000 3$
b01011111 4$
05$
H6$
H7$
L8$
09$
1:$
H;$
H<$
L=$
L>$
H?$
0@$
0A$
HB$
0C$
b11110101 D$
1E$
0F$
b11110101 G$
0H$
0I$
HJ$
LK$
b01011111 L$
0M$
1N$
b01011111 O$
#20000000
0&
0-
01
07
0=
0A
0I
0S
0W
0Z
1]
0m
1o
1w
0&"
0,"
00"
07"
1:"
0F"
1L"
1T"
0`"
0j"
0n"
0q"
1t"
0'#
1)#
11#
0=#
0C#
0G#
0K#
0N#
1Q#
0]#
0a#
1c#
1k#
0w#
0}#
0$$
0+$
1.$
0:$
1@$
1H$
#40000000
1)
#45000000
1'
0(
1.
b000000000000000000000000000000000000000000000000000000000000000000000000000000000000000000000001 D
1J
0Q
1X
0Y
1[
0\
1^
b000001 a
b000001 b
1n
1q
1r
0t
1u
b01101000 v
1y
1|
0}
b10011001 !"
1'"
1-"
18"
b000001 >"
b000001 ?"
1G"
1N"
b10000100 S"
1V"
b0111101L ["
#50000000
0'
0.
0J
0X
0[
0n
0q
0y
0'"
0-"
08"
0G"
0N"
0V"
#55000000
1'
1(
1.
0/
b000000000000000000000000000000000000000000000000000000000000000000000000000000000000000000000010 D
1J
0K
1Q
1X
1Y
1[
1\
0^
0_
b000010 a
b000010 b
0g
1n
1q
0r
1t
0u
b11010001 v
1y
0z
0|
1}
b00110011 !"
1'"
1-"
0."
06"
18"
09"
1;"
b000010 >"
b000010 ?"
1G"
1N"
1O"
0Q"
1R"
b00001000 S"
1V"
1Y"
0Z"
b111101LL ["
#60000000
0'
0.
0J
0X
0[
0n
0q
0y
0'"
0-"
08"
0G"
0N"
0V"
#65000000
1'
1.
b000000000000000000000000000000000000000000000000000000000000000000000000000000000000000000000101 D
1J
1X
1[
b000011 a
b000011 b
1n
1q
b10100010 v
1y
b01100110 !"
1'"
1-"
18"
b000011 >"
b000011 ?"
1G"
1N"
b00010001 S"
1V"
b11101LLL ["
#70000000
0'
0.
0J
0X
0[
0n
0q
0y
0'"
0-"
08"
0G"
0N"
0V"
#75000000
1'
0(
1.
b000000000000000000000000000000000000000000000000000000000000000000000000000000000000000000001011 D
1J
0Q
1X
0Y
1[
0\
1^
b000100 a
b000100 b
1n
1q
1r
0t
1u
b01000100 v
1y
1|
0}
b11001100 !"
1'"
1-"
18"
b000100 >"
b000100 ?"
1G"
1N"
b00100011 S"
1V"
b1101LLLL ["
#80000000
0'
0.
0J
0X
0[
0n
0q
0y
0'"
0-"
08"
0G"
0N"
0V"
#85000000
1'
1(
1.
b000000000000000000000000000000000000000000000000000000000000000000000000000000000000000000010110 D
1J
1Q
1X
1Y
1[
1\
b000101 a
b000101 b
1n
1q
1t
0u
b10001001 v
1y
b10011000 !"
1'"
1-"
18"
b000101 >"
b000101 ?"
1G"
1N"
b01000111 S"
1V"
b101LLLLL ["
#90000000
0'
0.
0J
0X
0[
0n
0q
0y
0'"
0-"
08"
0G"
0N"
0V"
#95000000
1'
0(
1.
1/
b000000000000000000000000000000000000000000000000000000000000000000000000000000000000000000101101 D
1J
1K
0Q
1X
0Y
1[
0\
0^
1_
b000110 a
b000110 b
1g
1n
1q
0r
0t
1u
b00010011 v
1y
1z
0|
1}
b00110000 !"
1'"
1-"
1."
16"
18"
19"
0;"
b000110 >"
b000110 ?"
1G"
1N"
0O"
1Q"
0R"
b10001111 S"
1V"
0Y"
1Z"
b01LLLLLL ["
#100000000
0'
0.
0J
0X
0[
0n
0q
0y
0'"
0-"
08"
0G"
0N"
0V"
#105000000
1'
1.
0/
b000000000000000000000000000000000000000000000000000000000000000000000000000000000000000001011010 D
1J
0K
1X
1[
0_
b000111 a
b000111 b
0g
1n
1q
b00100110 v
1y
0z
b01100001 !"
1'"
1-"
0."
06"
18"
09"
1;"
b000111 >"
b000111 ?"
1G"
1N"
1O"
0Q"
1R"
b00011110 S"
1V"
1Y"
0Z"
b1LLLLLLL ["
#110000000
0'
0.
0J
0X
0[
0n
0q
0y
0'"
0-"
08"
0G"
0N"
0V"
#115000000
1'
1.
b000000000000000000000000000000000000000000000000000000000000000000000000000000000000000010110100 D
1J
1X
1[
1^
b001000 a
b001000 b
1n
1q
1r
b01001100 v
1y
1|
0}
b11000010 !"
1'"
1-"
18"
L;"
b001000 >"
b001000 ?"
1G"
1N"
LO"
b00111101 S"
1V"
LY"
1Z"
bLLLLLLLL ["
#120000000
0'
0.
0J
0X
0[
0n
0q
0y
0'"
0-"
08"
0G"
0N"
0V"
#125000000
1'
1(
1.
b000000000000000000000000000000000000000000000000000000000000000000000000000000000000000101101000 D
1J
1Q
1X
1Y
1[
1\
b001001 a
b001001 b
1n
1q
1t
0u
b10011001 v
1y
b10000100 !"
1'"
1-"
18"
b001001 >"
b001001 ?"
1G"
1N"
b0111101L S"
1V"
#130000000
0'
0.
0J
0X
0[
0n
0q
0y
0'"
0-"
08"
0G"
0N"
0V"
#135000000
1'
0(
1.
1/
b000000000000000000000000000000000000000000000000000000000000000000000000000000000000001011010001 D
1J
1K
0Q
1X
0Y
1[
0\
0^
1_
b001010 a
b001010 b
1g
1n
1q
0r
0t
1u
b00110011 v
1y
1z
0|
1}
b00001000 !"
1'"
1-"
1."
16"
18"
19"
b001010 >"
b001010 ?"
1G"
1N"
1Q"
0R"
b111101LL S"
1V"
#140000000
0'
0.
0J
0X
0[
0n
0q
0y
0'"
0-"
08"
0G"
0N"
0V"
#145000000
1'
1.
b000000000000000000000000000000000000000000000000000000000000000000000000000000000000010110100010 D
1J
1X
1[
b001011 a
b001011 b
1n
1q
b01100110 v
1y
b00010001 !"
1'"
1-"
18"
b001011 >"
b001011 ?"
1G"
1N"
b11101LLL S"
1V"
#150000000
0'
0.
0J
0X
0[
0n
0q
0y
0'"
0-"
08"
0G"
0N"
0V"
#155000000
1'
1(
1.
b000000000000000000000000000000000000000000000000000000000000000000000000000000000000101101000100 D
1J
1Q
1X
1Y
1[
1\
b001100 a
b001100 b
1n
1q
1t
0u
b11001100 v
1y
b00100011 !"
1'"
1-"
18"
b001100 >"
b001100 ?"
1G"
1N"
b1101LLLL S"
1V"
