hardware/simulation/74hc165.vhdl
library IEEE;
use IEEE.std_logic_1164.all;

entity T74HCT165 is
port (
    nPL                 : IN  std_logic;
    nCE                : IN  std_logic;
    CP                  : IN  std_logic;
    DS                  : IN  std_logic;
    D                    : IN  std_logic_vector(7 downto 0);
    Q7                  : OUT std_logic;
    nQ7                : OUT std_logic
);
end T74HCT165;

architecture behave_T74HCT165 of T74HCT165 is
signal  Qs            : std_logic_vector(7 downto 0) ;

begin
HCT165 : process(nPL, CP, D)
begin
    if(nPL = '0') then
        Qs <= D;
    elsif rising_edge(CP) then
        if(nCE = '0') then
            Qs <= Qs(6 downto 0) & DS;    -- or  Qs <= shl(Qs, '1') & DS;
        end if;
    end if;
end process;
    Q7 <= Qs(7);
    nQ7 <= not(Qs(7));
end behave_T74HCT165;

hardware/simulation/tile.vhdl
library ieee;
use ieee.std_logic_1164.all;
use IEEE.NUMERIC_STD.ALL;

entity tile is
  port (
    buttons : in std_logic_vector(11 downto 0) := (others => 'L');

    T_W : in std_logic := '1';
    T_endcol : in std_logic := '1';
    T_first : out std_logic := '0';
    T_latch : out std_logic;
    T_clk : out std_logic := '0';
    T_data : in std_logic := '0';

    B_W : out std_logic;
    B_endcol : out std_logic := '0';
    B_first : in std_logic := '1';
    B_latch : in std_logic := '0';
    B_clk : in std_logic := '0';
    B_data : out std_logic;

    L_endrow : in std_logic := '1';
    L_latch : out std_logic := '0';
    L_clk : out std_logic := '0';
    L_data : in std_logic := '0';

    R_endrow : out std_logic := '0';
    R_latch : in std_logic := '0';
    R_clk : in std_logic := '0';
    R_data : out std_logic
  );
end tile;

architecture rtl of tile is

signal latch, clock, data : std_logic; -- sengnali principali
signal nlatch : std_logic;

signal ds_bridge : std_logic; -- sengale per connettere l'uscita seriale di SR2 a SR1
signal ds_input : std_logic; -- ds in input dai moduli adiacenti

signal w_state : std_logic; -- stato dei buffer 3state

signal count_reg : unsigned(5 downto 0) := (others => '0'); -- contatore
signal count : std_logic_vector(5 downto 0);

signal sr2_inputs : std_logic_vector(7 downto 0); -- Segnale di supporto
signal ffinput : std_logic;

begin

  clock <= 'H';
  nlatch <= not latch;

  -- sr LSB
  sr1 : entity work.T74HCT165
    port map(
      nPL => nlatch,
      nCE => '0',
      CP => clock,
      DS => ds_bridge,
      D => buttons(11 downto 4),
      Q7 => data,
      nQ7 => open
    );

  sr2_inputs <= buttons(3 downto 0) & "11" & L_endrow & T_endcol;

  -- sr MSB
  sr2 : entity work.T74HCT165
    port map(
      nPL => nlatch,
      nCE => '0',
      CP => clock,
      DS => ds_input,
      D => sr2_inputs,
      Q7 => ds_bridge,
      nQ7 => open
    );


  -- I/O latch clock e data
  --latch <= R_latch;
  --clock <= R_clk;
  R_data <= data;

  T_latch <= latch;
  T_clk <= clock when w_state = '0' else 'Z';

  --latch <= B_latch;
  --clock <= B_clk;
  B_data <= data;

  L_latch <= latch;
  L_clk <= clock when w_state = '1' else 'Z';

  ds_input <= T_data when w_state = '0' else L_data;

  latch <= R_latch or B_latch;  -- il latch è come un reset quindi lo mettiamo in or



  -- controllo di w_state
  w_state <= T_W and B_first;


  process(clock, latch)
  begin
    if latch = '1' then
      count_reg <= (others => '0');
    elsif rising_edge(clock) then
      count_reg <= count_reg + 1;
    end if;
  end process;

  count <= std_logic_vector(count_reg);
  ffinput <= count(3) and count(2) and count(1) and count(0) and data;

  process(clock, latch)
  begin
    if latch = '1' then
      B_W <= '0';
    elsif rising_edge(clock) then
      if ffinput = '1' then
        B_W <= '1';
      end if;
    end if;
  end process;


  -- il pezzo sotto serve solo a non far incazzare GHDL
  clock <= R_clk when to_x01(B_first) = '1' else B_clk;


end rtl;

hardware/simulation/tile_tb.vhdl
library ieee;
use ieee.std_logic_1164.all;
use ieee.numeric_std.all;

entity tile_tb is
end tile_tb;

architecture sim of tile_tb is

  signal buttons11    : std_logic_vector(11 downto 0) := x"A53"; -- 1010 0101 0011
  signal buttons21    : std_logic_vector(11 downto 0) := x"B31";
  signal buttons12    : std_logic_vector(11 downto 0) := x"5F9";

  signal latch, clk, data : std_logic;

  constant CLK_PERIOD : time := 10 ns;

  signal clk_en : std_logic := '0';

  -- sengali di collegamento fra 11 e 21
  signal W_11_21, endcol_11_21, first_11_21, latch_11_21, clock_11_21, data_11_21 : std_logic;
  -- sengali di collegamento fra 11 e 12
  signal endrow_11_12, latch_11_12, clock_11_12, data_11_12 : std_logic;


  signal sr_controllo : std_logic_vector(63 downto 0) := (others => '0');

begin

    -- Istanza del tuo modulo
    uut11: entity work.tile
        port map (
            buttons => buttons11,
            T_W => W_11_21,
            T_endcol => endcol_11_21,
            T_first => first_11_21,
            T_latch => latch_11_21,
            T_clk => clock_11_21,
            t_data => data_11_21,
            B_W => open,
            B_endcol => open,
            B_data => open,
            L_endrow => endrow_11_12,
            L_latch => latch_11_12,
            L_clk => clock_11_12,
            L_data => data_11_12,
            R_endrow => open,
            R_latch => latch,
            R_clk => clk,
            R_data => data
        );

    uut21: entity work.tile
        port map (
            buttons => buttons21,
            T_first => open,
            T_latch => open,
            T_clk => open,
            B_W => W_11_21,
            B_endcol => endcol_11_21,
            B_first => first_11_21,
            B_latch => latch_11_21,
            B_clk => clock_11_21,
            B_data => data_11_21,
            L_latch => open,
            L_clk => open,
            R_endrow => open,
            R_data => open
        );

    uut12: entity work.tile
        port map (
            buttons => buttons12,
            T_first => open,
            T_latch => open,
            T_clk => open,
            B_W => open,
            B_endcol => open,
            B_data => open,
            L_latch => open,
            L_clk => open,
            R_endrow => endrow_11_12,
            R_data => data_11_12,
            R_clk => clock_11_12,
            R_latch => latch_11_12
        );

    -- Generatore di Clock (sulla linea R_clk)
    clk_process : process  -- RIMOSSO (clk_en)
    begin
        while now < 500 ns loop
            if clk_en = '1' then
                clk <= '0';
                wait for CLK_PERIOD/2;
                clk <= '1';
                wait for CLK_PERIOD/2;
            else
                clk <= '0';
                -- Fondamentale: se il clock è disabilitato, dobbiamo
                -- aspettare che clk_en cambi, altrimenti il loop gira
                -- all'infinito nello stesso istante di tempo (hang).
                wait until clk_en = '1';
            end if;
        end loop;
        wait; -- Ferma tutto dopo 500 ns
    end process;



    capture_data: process(clk)
    begin
        if rising_edge(clk) then
            if latch = '0' then
                -- shift a sinistra: il nuovo bit entra dalla posizione 0
                sr_controllo <= sr_controllo(62 downto 0) & data;
            end if;
        end if;
    end process;



    -- Stimolo principale
    stim_proc: process
    begin

        latch <= '1';  -- stato di reset
        wait for 5 ns;
        latch <= '0'; -- shifting

        clk_en <= '1';
        wait for CLK_PERIOD * 100;
        clk_en <= '0';

        wait for 20 ns;





        --wait for CLK_PERIOD * 2;
        wait;
    end process;

end sim;

hardware/simulation/tile.vcd
$date
  Thu Jan  8 12:45:52 2026
$end
$version
  GHDL v0
$end
$timescale
  1 fs
$end
$scope module standard $end
$upscope $end
$scope module std_logic_1164 $end
$upscope $end
$scope module numeric_std $end
$upscope $end
$scope module tile_tb $end
$var reg 12 ! buttons11[11:0] $end
$var reg 12 " buttons21[11:0] $end
$var reg 12 # buttons12[11:0] $end
$var reg 1 $ latch $end
$var reg 1 % clk $end
$var reg 1 & data $end
$var reg 1 ' clk_en $end
$var reg 1 ( w_11_21 $end
$var reg 1 ) endcol_11_21 $end
$var reg 1 * first_11_21 $end
$var reg 1 + latch_11_21 $end
$var reg 1 , clock_11_21 $end
$var reg 1 - data_11_21 $end
$var reg 1 . endrow_11_12 $end
$var reg 1 / latch_11_12 $end
$var reg 1 0 clock_11_12 $end
$var reg 1 1 data_11_12 $end
$var reg 64 2 sr_controllo[63:0] $end
$scope module uut11 $end
$var reg 12 3 buttons[11:0] $end
$var reg 1 4 t_w $end
$var reg 1 5 t_endcol $end
$var reg 1 6 t_first $end
$var reg 1 7 t_latch $end
$var reg 1 8 t_clk $end
$var reg 1 9 t_data $end
$var reg 1 : b_w $end
$var reg 1 ; b_endcol $end
$var reg 1 < b_first $end
$var reg 1 = b_latch $end
$var reg 1 > b_clk $end
$var reg 1 ? b_data $end
$var reg 1 @ l_endrow $end
$var reg 1 A l_latch $end
$var reg 1 B l_clk $end
$var reg 1 C l_data $end
$var reg 1 D r_endrow $end
$var reg 1 E r_latch $end
$var reg 1 F r_clk $end
$var reg 1 G r_data $end
$var reg 1 H latch $end
$var reg 1 I clock $end
$var reg 1 J data $end
$var reg 1 K nlatch $end
$var reg 1 L ds_bridge $end
$var reg 1 M ds_input $end
$var reg 1 N w_state $end
$var reg 6 O count_reg[5:0] $end
$var reg 6 P count[5:0] $end
$var reg 8 Q sr2_inputs[7:0] $end
$var reg 1 R ffinput $end
$scope module sr1 $end
$var reg 1 S npl $end
$var reg 1 T nce $end
$var reg 1 U cp $end
$var reg 1 V ds $end
$var reg 8 W d[7:0] $end
$var reg 1 X q7 $end
$var reg 1 Y nq7 $end
$var reg 8 Z qs[7:0] $end
$upscope $end
$scope module sr2 $end
$var reg 1 [ npl $end
$var reg 1 \ nce $end
$var reg 1 ] cp $end
$var reg 1 ^ ds $end
$var reg 8 _ d[7:0] $end
$var reg 1 ` q7 $end
$var reg 1 a nq7 $end
$var reg 8 b qs[7:0] $end
$upscope $end
$upscope $end
$scope module uut21 $end
$var reg 12 c buttons[11:0] $end
$var reg 1 d t_w $end
$var reg 1 e t_endcol $end
$var reg 1 f t_first $end
$var reg 1 g t_latch $end
$var reg 1 h t_clk $end
$var reg 1 i t_data $end
$var reg 1 j b_w $end
$var reg 1 k b_endcol $end
$var reg 1 l b_first $end
$var reg 1 m b_latch $end
$var reg 1 n b_clk $end
$var reg 1 o b_data $end
$var reg 1 p l_endrow $end
$var reg 1 q l_latch $end
$var reg 1 r l_clk $end
$var reg 1 s l_data $end
$var reg 1 t r_endrow $end
$var reg 1 u r_latch $end
$var reg 1 v r_clk $end
$var reg 1 w r_data $end
$var reg 1 x latch $end
$var reg 1 y clock $end
$var reg 1 z data $end
$var reg 1 { nlatch $end
$var reg 1 | ds_bridge $end
$var reg 1 } ds_input $end
$var reg 1 !" w_state $end
$var reg 6 "" count_reg[5:0] $end
$var reg 6 #" count[5:0] $end
$var reg 8 $" sr2_inputs[7:0] $end
$var reg 1 %" ffinput $end
$scope module sr1 $end
$var reg 1 &" npl $end
$var reg 1 '" nce $end
$var reg 1 (" cp $end
$var reg 1 )" ds $end
$var reg 8 *" d[7:0] $end
$var reg 1 +" q7 $end
$var reg 1 ," nq7 $end
$var reg 8 -" qs[7:0] $end
$upscope $end
$scope module sr2 $end
$var reg 1 ." npl $end
$var reg 1 /" nce $end
$var reg 1 0" cp $end
$var reg 1 1" ds $end
$var reg 8 2" d[7:0] $end
$var reg 1 3" q7 $end
$var reg 1 4" nq7 $end
$var reg 8 5" qs[7:0] $end
$upscope $end
$upscope $end
$scope module uut12 $end
$var reg 12 6" buttons[11:0] $end
$var reg 1 7" t_w $end
$var reg 1 8" t_endcol $end
$var reg 1 9" t_first $end
$var reg 1 :" t_latch $end
$var reg 1 ;" t_clk $end
$var reg 1 <" t_data $end
$var reg 1 =" b_w $end
$var reg 1 >" b_endcol $end
$var reg 1 ?" b_first $end
$var reg 1 @" b_latch $end
$var reg 1 A" b_clk $end
$var reg 1 B" b_data $end
$var reg 1 C" l_endrow $end
$var reg 1 D" l_latch $end
$var reg 1 E" l_clk $end
$var reg 1 F" l_data $end
$var reg 1 G" r_endrow $end
$var reg 1 H" r_latch $end
$var reg 1 I" r_clk $end
$var reg 1 J" r_data $end
$var reg 1 K" latch $end
$var reg 1 L" clock $end
$var reg 1 M" data $end
$var reg 1 N" nlatch $end
$var reg 1 O" ds_bridge $end
$var reg 1 P" ds_input $end
$var reg 1 Q" w_state $end
$var reg 6 R" count_reg[5:0] $end
$var reg 6 S" count[5:0] $end
$var reg 8 T" sr2_inputs[7:0] $end
$var reg 1 U" ffinput $end
$scope module sr1 $end
$var reg 1 V" npl $end
$var reg 1 W" nce $end
$var reg 1 X" cp $end
$var reg 1 Y" ds $end
$var reg 8 Z" d[7:0] $end
$var reg 1 [" q7 $end
$var reg 1 \" nq7 $end
$var reg 8 ]" qs[7:0] $end
$upscope $end
$scope module sr2 $end
$var reg 1 ^" npl $end
$var reg 1 _" nce $end
$var reg 1 `" cp $end
$var reg 1 a" ds $end
$var reg 8 b" d[7:0] $end
$var reg 1 c" q7 $end
$var reg 1 d" nq7 $end
$var reg 8 e" qs[7:0] $end
$upscope $end
$upscope $end
$upscope $end
$enddefinitions $end
#0
b101001010011 !
b101100110001 "
b010111111001 #
1$
0%
1&
0'
0(
0)
0*
1+
0,
1-
0.
1/
Z0
01
b0000000000000000000000000000000000000000000000000000000000000000 2
b101001010011 3
04
05
06
17
08
19
0:
0;
1<
0=
0>
1?
0@
1A
ZB
0C
0D
1E
0F
1G
1H
0I
1J
0K
0L
1M
0N
b000000 O
b000000 P
b00111100 Q
0R
0S
0T
0U
0V
b10100101 W
1X
0Y
b10100101 Z
0[
0\
0]
1^
b00111100 _
0`
1a
b00111100 b
b101100110001 c
1d
1e
0f
1g
0h
0i
0j
0k
0l
1m
0n
1o
1p
1q
Zr
0s
0t
0u
0v
1w
1x
0y
1z
0{
0|
0}
0!"
b000000 ""
b000000 #"
b00011111 $"
0%"
0&"
0'"
0("
0)"
b10110011 *"
1+"
0,"
b10110011 -"
0."
0/"
00"
01"
b00011111 2"
03"
14"
b00011111 5"
b010111111001 6"
17"
18"
09"
1:"
Z;"
0<"
0="
0>"
1?"
0@"
0A"
0B"
1C"
1D"
HE"
0F"
0G"
1H"
ZI"
0J"
1K"
HL"
0M"
0N"
1O"
0P"
1Q"
b000000 R"
b000000 S"
b10011111 T"
0U"
0V"
0W"
HX"
1Y"
b01011111 Z"
0["
1\"
b01011111 ]"
0^"
0_"
H`"
0a"
b10011111 b"
1c"
0d"
b10011111 e"
#5000000
0$
1'
0+
0/
07
0A
0E
0H
1K
1S
1[
0g
0m
0q
0x
1{
1&"
1."
0:"
0D"
0H"
0K"
1N"
1V"
1^"
#10000000
1%
0&
1,
0-
b0000000000000000000000000000000000000000000000000000000000000001 2
18
09
0?
1F
0G
1I
0J
0M
b000001 O
b000001 P
1U
0X
1Y
b01001010 Z
1]
0^
b01111001 b
1h
1n
0o
0w
1y
0z
b000001 ""
b000001 #"
1("
0+"
1,"
b01100110 -"
10"
b00111110 5"
#15000000
0%
0,
08
0F
0I
0U
0]
0h
0n
0y
0("
00"
#20000000
1%
1&
1,
1-
b0000000000000000000000000000000000000000000000000000000000000010 2
18
19
1?
1F
1G
1I
1J
1L
1M
b000010 O
b000010 P
1U
1V
1X
0Y
b10010100 Z
1]
1^
1`
0a
b11110010 b
1h
1n
1o
1w
1y
1z
b000010 ""
b000010 #"
1("
1+"
0,"
b11001100 -"
10"
b01111100 5"
#25000000
0%
0,
08
0F
0I
0U
0]
0h
0n
0y
0("
00"
#30000000
1%
0&
1,
b0000000000000000000000000000000000000000000000000000000000000101 2
18
0?
1F
0G
1I
0J
b000011 O
b000011 P
1U
0X
1Y
b00101001 Z
1]
b11100101 b
1h
1n
1y
1|
b000011 ""
b000011 #"
1("
1)"
b10011000 -"
10"
13"
04"
b11111000 5"
#35000000
0%
0,
08
0F
0I
0U
0]
0h
0n
0y
0("
00"
#40000000
1%
1,
0-
b0000000000000000000000000000000000000000000000000000000000001010 2
18
09
1F
1I
0M
b000100 O
b000100 P
1U
b01010011 Z
1]
0^
b11001011 b
1h
1n
0o
0w
1y
0z
b000100 ""
b000100 #"
1("
0+"
1,"
b00110001 -"
10"
b11110000 5"
#45000000
0%
0,
08
0F
0I
0U
0]
0h
0n
0y
0("
00"
#50000000
1%
1&
1,
b0000000000000000000000000000000000000000000000000000000000010100 2
18
1?
1F
1G
1I
1J
b000101 O
b000101 P
1U
1X
0Y
b10100111 Z
1]
b10010110 b
1h
1n
1y
b000101 ""
b000101 #"
1("
b01100011 -"
10"
b11100000 5"
#55000000
0%
0,
08
0F
0I
0U
0]
0h
0n
0y
0("
00"
#60000000
1%
0&
1,
1-
b0000000000000000000000000000000000000000000000000000000000101001 2
18
19
0?
1F
0G
1I
0J
0L
1M
b000110 O
b000110 P
1U
0V
0X
1Y
b01001111 Z
1]
1^
0`
1a
b00101100 b
1h
1n
1o
1w
1y
1z
b000110 ""
b000110 #"
1("
1+"
0,"
b11000111 -"
10"
b11000000 5"
#65000000
0%
0,
08
0F
0I
0U
0]
0h
0n
0y
0("
00"
#70000000
1%
1&
1,
b0000000000000000000000000000000000000000000000000000000001010010 2
18
1?
1F
1G
1I
1J
b000111 O
b000111 P
1U
1X
0Y
b10011110 Z
1]
b01011001 b
1h
1n
1y
b000111 ""
b000111 #"
1("
b10001111 -"
10"
b10000000 5"
#75000000
0%
0,
08
0F
0I
0U
0]
0h
0n
0y
0("
00"
#80000000
1%
0&
1,
0-
b0000000000000000000000000000000000000000000000000000000010100101 2
18
09
0?
1F
0G
1I
0J
1L
0M
b001000 O
b001000 P
1U
1V
0X
1Y
b00111100 Z
1]
0^
1`
0a
b10110011 b
1h
1n
0o
0w
1y
0z
0|
b001000 ""
b001000 #"
1("
0)"
0+"
1,"
b00011111 -"
10"
03"
14"
b00000000 5"
#85000000
0%
0,
08
0F
0I
0U
0]
0h
0n
0y
0("
00"
#90000000
1%
1,
b0000000000000000000000000000000000000000000000000000000101001010 2
18
1F
1I
0L
b001001 O
b001001 P
1U
0V
b01111001 Z
1]
0`
1a
b01100110 b
1h
1n
1y
b001001 ""
b001001 #"
1("
b00111110 -"
10"
#95000000
0%
0,
08
0F
0I
0U
0]
0h
0n
0y
0("
00"
#100000000
1%
1&
1,
b0000000000000000000000000000000000000000000000000000001010010100 2
18
1?
1F
1G
1I
1J
1L
b001010 O
b001010 P
1U
1V
1X
0Y
b11110010 Z
1]
1`
0a
b11001100 b
1h
1n
1y
b001010 ""
b001010 #"
1("
b01111100 -"
10"
#105000000
0%
0,
08
0F
0I
0U
0]
0h
0n
0y
0("
00"
#110000000
1%
1,
1-
b0000000000000000000000000000000000000000000000000000010100101001 2
18
19
1F
1I
1M
b001011 O
b001011 P
1U
b11100101 Z
1]
1^
b10011000 b
1h
1n
1o
1w
1y
1z
b001011 ""
b001011 #"
1("
1+"
0,"
b11111000 -"
10"
#115000000
0%
0,
08
0F
0I
0U
0]
0h
0n
0y
0("
00"
#120000000
1%
1,
b0000000000000000000000000000000000000000000000000000101001010011 2
18
1F
1I
0L
b001100 O
b001100 P
1U
0V
b11001011 Z
1]
0`
1a
b00110001 b
1h
1n
1y
b001100 ""
b001100 #"
1("
b11110000 -"
10"
#125000000
0%
0,
08
0F
0I
0U
0]
0h
0n
0y
0("
00"
#130000000
1%
1,
b0000000000000000000000000000000000000000000000000001010010100111 2
18
1F
1I
b001101 O
b001101 P
1U
b10010110 Z
1]
b01100011 b
1h
1n
1y
b001101 ""
b001101 #"
1("
b11100000 -"
10"
#135000000
0%
0,
08
0F
0I
0U
0]
0h
0n
0y
0("
00"
#140000000
1%
0&
1,
b0000000000000000000000000000000000000000000000000010100101001111 2
18
0?
1F
0G
1I
0J
1L
b001110 O
b001110 P
1U
1V
0X
1Y
b00101100 Z
1]
1`
0a
b11000111 b
1h
1n
1y
b001110 ""
b001110 #"
1("
b11000000 -"
10"
#145000000
0%
0,
08
0F
0I
0U
0]
0h
0n
0y
0("
00"
#150000000
1%
1,
b0000000000000000000000000000000000000000000000000101001010011110 2
18
1F
1I
b001111 O
b001111 P
1U
b01011001 Z
1]
b10001111 b
1h
1n
1y
b001111 ""
b001111 #"
1%"
1("
b10000000 -"
10"
#155000000
0%
0,
08
0F
0I
0U
0]
0h
0n
0y
0("
00"
#160000000
1%
1&
1(
Z,
0-
10
b0000000000000000000000000000000000000000000000001010010100111100 2
14
Z8
09
1?
1B
1F
1G
1I
1J
0L
0M
1N
b010000 O
b010000 P
1U
0V
1X
0Y
b10110011 Z
1]
0^
0`
1a
b00011111 b
Hh
1j
Zn
0o
0w
Hy
0z
b010000 ""
b010000 #"
0%"
H("
0+"
1,"
b00000000 -"
H0"
1E"
1I"
1L"
1X"
1`"
#165000000
0%
00
0B
0F
0I
0U
0]
0E"
0I"
0L"
0X"
0`"
#170000000
1%
0&
10
11
b0000000000000000000000000000000000000000000000010100101001111001 2
0?
1B
1C
1F
0G
1I
0J
1M
b010001 O
b010001 P
1U
0X
1Y
b01100110 Z
1]
1^
b00111110 b
1B"
1E"
1I"
1J"
1L"
1M"
0O"
b000001 R"
b000001 S"
1X"
0Y"
1["
0\"
b10111111 ]"
1`"
0c"
1d"
b00111110 e"
#175000000
0%
00
0B
0F
0I
0U
0]
0E"
0I"
0L"
0X"
0`"
#180000000
1%
1&
10
01
b0000000000000000000000000000000000000000000000101001010011110010 2
1?
1B
0C
1F
1G
1I
1J
0M
b010010 O
b010010 P
1U
1X
0Y
b11001100 Z
1]
0^
b01111101 b
0B"
1E"
1I"
0J"
1L"
0M"
b000010 R"
b000010 S"
1X"
0["
1\"
b01111110 ]"
1`"
b01111100 e"
#185000000
0%
00
0B
0F
0I
0U
0]
0E"
0I"
0L"
0X"
0`"
#190000000
1%
10
11
b0000000000000000000000000000000000000000000001010010100111100101 2
1B
1C
1F
1I
1L
1M
b010011 O
b010011 P
1U
1V
b10011000 Z
1]
1^
1`
0a
b11111010 b
1B"
1E"
1I"
1J"
1L"
1M"
1O"
b000011 R"
b000011 S"
1X"
1Y"
1["
0\"
b11111100 ]"
1`"
1c"
0d"
b11111000 e"
#195000000
0%
00
0B
0F
0I
0U
0]
0E"
0I"
0L"
0X"
0`"
#200000000
1%
0&
10
b0000000000000000000000000000000000000000000010100101001111001011 2
0?
1B
1F
0G
1I
0J
b010100 O
b010100 P
1U
0X
1Y
b00110001 Z
1]
b11110101 b
1E"
1I"
1L"
b000100 R"
b000100 S"
1X"
b11111001 ]"
1`"
b11110000 e"
#205000000
0%
00
0B
0F
0I
0U
0]
0E"
0I"
0L"
0X"
0`"
#210000000
1%
10
b0000000000000000000000000000000000000000000101001010011110010110 2
1B
1F
1I
b010101 O
b010101 P
1U
b01100011 Z
1]
b11101011 b
1E"
1I"
1L"
b000101 R"
b000101 S"
1X"
b11110011 ]"
1`"
b11100000 e"
#215000000
0%
00
0B
0F
0I
0U
0]
0E"
0I"
0L"
0X"
0`"
#220000000
1%
1&
10
b0000000000000000000000000000000000000000001010010100111100101100 2
1?
1B
1F
1G
1I
1J
b010110 O
b010110 P
1U
1X
0Y
b11000111 Z
1]
b11010111 b
1E"
1I"
1L"
b000110 R"
b000110 S"
1X"
b11100111 ]"
1`"
b11000000 e"
#225000000
0%
00
0B
0F
0I
0U
0]
0E"
0I"
0L"
0X"
0`"
#230000000
1%
10
b0000000000000000000000000000000000000000010100101001111001011001 2
1B
1F
1I
b010111 O
b010111 P
1U
b10001111 Z
1]
b10101111 b
1E"
1I"
1L"
b000111 R"
b000111 S"
1X"
b11001111 ]"
1`"
b10000000 e"
#235000000
0%
00
0B
0F
0I
0U
0]
0E"
0I"
0L"
0X"
0`"
#240000000
1%
0&
10
b0000000000000000000000000000000000000000101001010011110010110011 2
0?
1B
1F
0G
1I
0J
0L
b011000 O
b011000 P
1U
0V
0X
1Y
b00011111 Z
1]
0`
1a
b01011111 b
1E"
1I"
1L"
0O"
b001000 R"
b001000 S"
1X"
0Y"
b10011111 ]"
1`"
0c"
1d"
b00000000 e"
#245000000
0%
00
0B
0F
0I
0U
0]
0E"
0I"
0L"
0X"
0`"
#250000000
1%
10
01
b0000000000000000000000000000000000000001010010100111100101100110 2
1B
0C
1F
1I
1L
0M
b011001 O
b011001 P
1U
1V
b00111110 Z
1]
0^
1`
0a
b10111111 b
0B"
1E"
1I"
0J"
1L"
0M"
b001001 R"
b001001 S"
1X"
0["
1\"
b00111110 ]"
1`"
#255000000
0%
00
0B
0F
0I
0U
0]
0E"
0I"
0L"
0X"
0`"
#260000000
1%
10
b0000000000000000000000000000000000000010100101001111001011001100 2
1B
1F
1I
0L
b011010 O
b011010 P
1U
0V
b01111101 Z
1]
0`
1a
b01111110 b
1E"
1I"
1L"
b001010 R"
b001010 S"
1X"
b01111100 ]"
1`"
#265000000
0%
00
0B
0F
0I
0U
0]
0E"
0I"
0L"
0X"
0`"
#270000000
1%
1&
10
11
b0000000000000000000000000000000000000101001010011110010110011000 2
1?
1B
1C
1F
1G
1I
1J
1L
1M
b011011 O
b011011 P
1U
1V
1X
0Y
b11111010 Z
1]
1^
1`
0a
b11111100 b
1B"
1E"
1I"
1J"
1L"
1M"
b001011 R"
b001011 S"
1X"
1["
0\"
b11111000 ]"
1`"
#275000000
0%
00
0B
0F
0I
0U
0]
0E"
0I"
0L"
0X"
0`"
#280000000
1%
10
b0000000000000000000000000000000000001010010100111100101100110001 2
1B
1F
1I
b011100 O
b011100 P
1U
b11110101 Z
1]
b11111001 b
1E"
1I"
1L"
b001100 R"
b001100 S"
1X"
b11110000 ]"
1`"
#285000000
0%
00
0B
0F
0I
0U
0]
0E"
0I"
0L"
0X"
0`"
#290000000
1%
10
b0000000000000000000000000000000000010100101001111001011001100011 2
1B
1F
1I
b011101 O
b011101 P
1U
b11101011 Z
1]
b11110011 b
1E"
1I"
1L"
b001101 R"
b001101 S"
1X"
b11100000 ]"
1`"
#295000000
0%
00
0B
0F
0I
0U
0]
0E"
0I"
0L"
0X"
0`"
#300000000
1%
10
b0000000000000000000000000000000000101001010011110010110011000111 2
1B
1F
1I
b011110 O
b011110 P
1U
b11010111 Z
1]
b11100111 b
1E"
1I"
1L"
b001110 R"
b001110 S"
1X"
b11000000 ]"
1`"
#305000000
0%
00
0B
0F
0I
0U
0]
0E"
0I"
0L"
0X"
0`"
#310000000
1%
10
b0000000000000000000000000000000001010010100111100101100110001111 2
1B
1F
1I
b011111 O
b011111 P
1R
1U
b10101111 Z
1]
b11001111 b
1E"
1I"
1L"
b001111 R"
b001111 S"
1U"
1X"
b10000000 ]"
1`"
#315000000
0%
00
0B
0F
0I
0U
0]
0E"
0I"
0L"
0X"
0`"
#320000000
1%
0&
10
01
b0000000000000000000000000000000010100101001111001011001100011111 2
1:
0?
1B
0C
1F
0G
1I
0J
0M
b100000 O
b100000 P
0R
1U
0X
1Y
b01011111 Z
1]
0^
b10011111 b
1="
0B"
1E"
1I"
0J"
1L"
0M"
b010000 R"
b010000 S"
0U"
1X"
0["
1\"
b00000000 ]"
1`"
#325000000
0%
00
0B
0F
0I
0U
0]
0E"
0I"
0L"
0X"
0`"
#330000000
1%
1&
10
b0000000000000000000000000000000101001010011110010110011000111110 2
1?
1B
1F
1G
1I
1J
0L
b100001 O
b100001 P
1U
0V
1X
0Y
b10111111 Z
1]
0`
1a
b00111110 b
1E"
1I"
1L"
b010001 R"
b010001 S"
1X"
1`"
#335000000
0%
00
0B
0F
0I
0U
0]
0E"
0I"
0L"
0X"
0`"
#340000000
1%
0&
10
b0000000000000000000000000000001010010100111100101100110001111101 2
0?
1B
1F
0G
1I
0J
b100010 O
b100010 P
1U
0X
1Y
b01111110 Z
1]
b01111100 b
1E"
1I"
1L"
b010010 R"
b010010 S"
1X"
1`"
#345000000
0%
00
0B
0F
0I
0U
0]
0E"
0I"
0L"
0X"
0`"
#350000000
1%
1&
10
b0000000000000000000000000000010100101001111001011001100011111010 2
1?
1B
1F
1G
1I
1J
1L
b100011 O
b100011 P
1U
1V
1X
0Y
b11111100 Z
1]
1`
0a
b11111000 b
1E"
1I"
1L"
b010011 R"
b010011 S"
1X"
1`"
#355000000
0%
00
0B
0F
0I
0U
0]
0E"
0I"
0L"
0X"
0`"
#360000000
1%
10
b0000000000000000000000000000101001010011110010110011000111110101 2
1B
1F
1I
b100100 O
b100100 P
1U
b11111001 Z
1]
b11110000 b
1E"
1I"
1L"
b010100 R"
b010100 S"
1X"
1`"
#365000000
0%
00
0B
0F
0I
0U
0]
0E"
0I"
0L"
0X"
0`"
#370000000
1%
10
b0000000000000000000000000001010010100111100101100110001111101011 2
1B
1F
1I
b100101 O
b100101 P
1U
b11110011 Z
1]
b11100000 b
1E"
1I"
1L"
b010101 R"
b010101 S"
1X"
1`"
#375000000
0%
00
0B
0F
0I
0U
0]
0E"
0I"
0L"
0X"
0`"
#380000000
1%
10
b0000000000000000000000000010100101001111001011001100011111010111 2
1B
1F
1I
b100110 O
b100110 P
1U
b11100111 Z
1]
b11000000 b
1E"
1I"
1L"
b010110 R"
b010110 S"
1X"
1`"
#385000000
0%
00
0B
0F
0I
0U
0]
0E"
0I"
0L"
0X"
0`"
#390000000
1%
10
b0000000000000000000000000101001010011110010110011000111110101111 2
1B
1F
1I
b100111 O
b100111 P
1U
b11001111 Z
1]
b10000000 b
1E"
1I"
1L"
b010111 R"
b010111 S"
1X"
1`"
#395000000
0%
00
0B
0F
0I
0U
0]
0E"
0I"
0L"
0X"
0`"
#400000000
1%
10
b0000000000000000000000001010010100111100101100110001111101011111 2
1B
1F
1I
0L
b101000 O
b101000 P
1U
0V
b10011111 Z
1]
0`
1a
b00000000 b
1E"
1I"
1L"
b011000 R"
b011000 S"
1X"
1`"
#405000000
0%
00
0B
0F
0I
0U
0]
0E"
0I"
0L"
0X"
0`"
#410000000
1%
0&
10
b0000000000000000000000010100101001111001011001100011111010111111 2
0?
1B
1F
0G
1I
0J
b101001 O
b101001 P
1U
0X
1Y
b00111110 Z
1]
1E"
1I"
1L"
b011001 R"
b011001 S"
1X"
1`"
#415000000
0%
00
0B
0F
0I
0U
0]
0E"
0I"
0L"
0X"
0`"
#420000000
1%
10
b0000000000000000000000101001010011110010110011000111110101111110 2
1B
1F
1I
b101010 O
b101010 P
1U
b01111100 Z
1]
1E"
1I"
1L"
b011010 R"
b011010 S"
1X"
1`"
#425000000
0%
00
0B
0F
0I
0U
0]
0E"
0I"
0L"
0X"
0`"
