hardware/simulation/74hc165.vhdl
library IEEE;
use IEEE.std_logic_1164.all;

entity T74HCT165 is
port (
    nPL                 : IN  std_logic;
    nCE                : IN  std_logic;
    CP                  : IN  std_logic;
    DS                  : IN  std_logic;
    D                    : IN  std_logic_vector(7 downto 0);
    Q7                  : OUT std_logic;
    nQ7                : OUT std_logic
);
end T74HCT165;

architecture behave_T74HCT165 of T74HCT165 is
signal  Qs            : std_logic_vector(7 downto 0) ;

begin
HCT165 : process(nPL, CP, D)
begin
    if(nPL = '0') then
        Qs <= D;
    elsif(CP'event and CP = '1') then
        if(nCE = '0') then
            Qs <= Qs(6 downto 0) & DS;    -- or  Qs <= shl(Qs, '1') & DS;
        end if;
    end if;
end process;
    Q7 <= Qs(7);
    nQ7 <= not(Qs(7));
end behave_T74HCT165;

hardware/simulation/tile.vhdl
library ieee;
use ieee.std_logic_1164.all;
use IEEE.NUMERIC_STD.ALL;

entity tile is
  port (
    buttons : in std_logic_vector(11 downto 0) := (others => 'L');

    T_W : in std_logic := '1';
    T_endcol : in std_logic := '1';
    T_first : out std_logic := '0';
    T_latch : out std_logic;
    T_clk : out std_logic := '0';
    T_data : in std_logic := '0';

    B_W : out std_logic;
    B_endcol : out std_logic := '0';
    B_first : in std_logic := '1';
    B_latch : in std_logic := '0';
    B_clk : in std_logic := '0';
    B_data : out std_logic;

    L_endrow : in std_logic := '1';
    L_latch : out std_logic := '0';
    L_clk : out std_logic := '0';
    L_data : in std_logic := '0';

    R_endrow : out std_logic := '0';
    R_latch : in std_logic := '0';
    R_clk : in std_logic := '0';
    R_data : out std_logic
  );
end tile;

architecture rtl of tile is

signal latch, clock, data : std_logic; -- sengnali principali
signal nlatch : std_logic;

signal ds_bridge : std_logic; -- sengale per connettere l'uscita seriale di SR2 a SR1
signal ds_input : std_logic; -- ds in input dai moduli adiacenti

signal w_state : std_logic; -- stato dei buffer 3state

signal count_reg : unsigned(5 downto 0) := (others => '0'); -- contatore
signal count : std_logic_vector(5 downto 0);

signal sr2_inputs : std_logic_vector(7 downto 0); -- Segnale di supporto
signal ffinput : std_logic;

begin

  clock <= 'H';
  nlatch <= not latch;

  -- sr LSB
  sr1 : entity work.T74HCT165
    port map(
      nPL => nlatch,
      nCE => '0',
      CP => clock,
      DS => ds_bridge,
      D => buttons(11 downto 4),
      Q7 => data,
      nQ7 => open
    );

  sr2_inputs <= buttons(3 downto 0) & "11" & L_endrow & T_endcol;

  -- sr MSB
  sr2 : entity work.T74HCT165
    port map(
      nPL => nlatch,
      nCE => '0',
      CP => clock,
      DS => ds_input,
      D => sr2_inputs,
      Q7 => ds_bridge,
      nQ7 => open
    );


  -- I/O latch clock e data
  --latch <= R_latch;
  --clock <= R_clk;
  R_data <= data;

  T_latch <= latch;
  T_clk <= clock when w_state = '0' else 'Z';

  --latch <= B_latch;
  --clock <= B_clk;
  B_data <= data;

  L_latch <= latch;
  L_clk <= clock when w_state = '1' else 'Z';

  ds_input <= T_data when w_state = '0' else L_data;

  latch <= R_latch or B_latch;  -- il latch è come un reset quindi lo mettiamo in or



  -- controllo di w_state
  w_state <= T_W and B_first;


  process(clock, latch)
  begin
    if latch = '1' then
      count_reg <= (others => '0');
    elsif rising_edge(clock) then
      count_reg <= count_reg + 1;
    end if;
  end process;

  count <= std_logic_vector(count_reg);
  ffinput <= count(3) and count(2) and count(1) and count(0) and data;

  process(clock, latch)
  begin
    if latch = '1' then
      B_W <= '0';
    elsif rising_edge(clock) then
      if ffinput = '1' then
        B_W <= '1';
      end if;
    end if;
  end process;


  -- il pezzo sotto serve solo a non far incazzare GHDL
  clock <= R_clk when to_x01(B_first) = '1' else B_clk;


end rtl;

hardware/simulation/tile_tb.vhdl
library ieee;
use ieee.std_logic_1164.all;
use ieee.numeric_std.all;

entity tile_tb is
end tile_tb;

architecture sim of tile_tb is

  signal buttons11    : std_logic_vector(11 downto 0);
  signal buttons21    : std_logic_vector(11 downto 0);
  signal buttons12    : std_logic_vector(11 downto 0);
  signal buttons13    : std_logic_vector(11 downto 0);
  signal buttons23    : std_logic_vector(11 downto 0);
  signal buttons33    : std_logic_vector(11 downto 0);

  signal latch, clk, data : std_logic;

  constant CLK_PERIOD : time := 10 ns;

  signal clk_en : std_logic := '0';

  -- sengali di collegamento fra 11 e 21
  signal W_11_21, endcol_11_21, first_11_21, latch_11_21, clock_11_21, data_11_21 : std_logic;
  -- sengali di collegamento fra 11 e 12
  signal endrow_11_12, latch_11_12, clock_11_12, data_11_12 : std_logic;
  -- sengali di collegamento fra 12 e 13
  signal endrow_12_13, latch_12_13, clock_12_13, data_12_13 : std_logic;
  -- sengali di collegamento fra 13 e 23
  signal W_13_23, endcol_13_23, first_13_23, latch_13_23, clock_13_23, data_13_23 : std_logic;
  -- sengali di collegamento fra 23 e 33
  signal W_23_33, endcol_23_33, first_23_33, latch_23_33, clock_23_33, data_23_33 : std_logic;


  signal sr_controllo : std_logic_vector(95 downto 0) := (others => '0');

begin

    -- Istanza del tuo modulo
    uut11: entity work.tile
        port map (
            buttons => buttons11,
            T_W => W_11_21,
            T_endcol => endcol_11_21,
            T_first => first_11_21,
            T_latch => latch_11_21,
            T_clk => clock_11_21,
            t_data => data_11_21,
            B_W => open,
            B_endcol => open,
            B_data => open,
            L_endrow => endrow_11_12,
            L_latch => latch_11_12,
            L_clk => clock_11_12,
            L_data => data_11_12,
            R_endrow => open,
            R_latch => latch,
            R_clk => clk,
            R_data => data
        );

    uut21: entity work.tile
        port map (
            buttons => buttons21,
            T_first => open,
            T_latch => open,
            T_clk => open,
            B_W => W_11_21,
            B_endcol => endcol_11_21,
            B_first => first_11_21,
            B_latch => latch_11_21,
            B_clk => clock_11_21,
            B_data => data_11_21,
            L_latch => open,
            L_clk => open,
            R_endrow => open,
            R_data => open
        );

    uut12: entity work.tile
        port map (
            buttons => buttons12,
            T_first => open,
            T_latch => open,
            T_clk => open,
            B_W => open,
            B_endcol => open,
            B_data => open,
            L_endrow => endrow_12_13,
            L_latch => latch_12_13,
            L_clk => clock_12_13,
            L_data => data_12_13,
            R_endrow => endrow_11_12,
            R_data => data_11_12,
            R_clk => clock_11_12,
            R_latch => latch_11_12
        );

    uut13: entity work.tile
        port map (
            buttons => buttons13,
            T_W => W_13_23,
            T_endcol => endcol_13_23,
            T_first => first_13_23,
            T_latch => latch_13_23,
            T_clk => clock_13_23,
            T_data => data_13_23,
            B_W => open,
            B_endcol => open,
            B_data => open,
            L_latch => open,
            L_clk => open,
            R_endrow => endrow_12_13,
            R_data => data_12_13,
            R_clk => clock_12_13,
            R_latch => latch_12_13
        );

    uut23: entity work.tile
        port map (
            buttons => buttons23,
            T_W => W_23_33,
            T_endcol => endcol_23_33,
            T_first => first_23_33,
            T_latch => latch_23_33,
            T_clk => clock_23_33,
            T_data => data_23_33,
            B_W => W_13_23,
            B_endcol => endcol_13_23,
            B_first => first_13_23,
            B_data => data_13_23,
            B_latch => latch_13_23,
            B_clk => clock_13_23,
            L_latch => open,
            L_clk => open,
            R_endrow => open,
            R_data => open
        );

    uut33: entity work.tile
        port map (
            buttons => buttons33,
            T_first => open,
            T_latch => open,
            T_clk => open,
            B_W => W_23_33,
            B_endcol => endcol_23_33,
            B_first => first_23_33,
            B_latch => latch_23_33,
            B_clk => clock_23_33,
            B_data => data_23_33,
            L_latch => open,
            L_clk => open,
            R_endrow => open,
            R_data => open
        );

    -- Generatore di Clock (sulla linea R_clk)
    clk_process : process  -- RIMOSSO (clk_en)
    begin
        while true loop
            if clk_en = '1' then
                clk <= '0';
                wait for CLK_PERIOD/2;
                clk <= '1';
                wait for CLK_PERIOD/2;
            else
                clk <= '0';
                -- Fondamentale: se il clock è disabilitato, dobbiamo
                -- aspettare che clk_en cambi, altrimenti il loop gira
                -- all'infinito nello stesso istante di tempo (hang).
                wait until clk_en = '1';
            end if;
        end loop;
        wait; -- Ferma tutto dopo 500 ns
    end process;



    capture_data: process(clk)
    begin
        if rising_edge(clk) then
            if latch = '0' then
                -- shift a sinistra: il nuovo bit entra dalla posizione 0
                sr_controllo <= sr_controllo(94 downto 0) & data;
            end if;
        end if;
    end process;



    -- Stimolo principale
    stim_proc: process
    begin

        buttons11 <= x"B44";
        buttons21 <= x"C23";
        buttons12 <= x"34D";
        buttons13 <= x"E11";
        buttons23 <= x"F55";
        buttons33 <= x"AA1";

        latch <= '1';  -- stato di reset
        wait for 20 ns;
        latch <= '0'; -- shifting
        wait for 20 ns;

        clk_en <= '1';
        wait for CLK_PERIOD * 95;
        clk_en <= '0';

        wait for 40 ns;




        buttons11 <= x"DF3";
        buttons21 <= x"A31";
        buttons12 <= x"000";
        buttons13 <= x"FFF";
        buttons23 <= x"A34";
        buttons33 <= x"843";

        latch <= '1';  -- stato di reset
        wait for 20 ns;
        latch <= '0'; -- shifting
        wait for 20 ns;

        clk_en <= '1';
        wait for CLK_PERIOD * 95;
        clk_en <= '0';

        wait for 40 ns;


        --wait for CLK_PERIOD * 2;
        wait;
    end process;

end sim;

hardware/simulation/tile.vcd
$date
  Thu Jan  8 13:29:07 2026
$end
$version
  GHDL v0
$end
$timescale
  1 fs
$end
$scope module standard $end
$upscope $end
$scope module std_logic_1164 $end
$upscope $end
$scope module numeric_std $end
$upscope $end
$scope module tile_tb $end
$var reg 12 ! buttons11[11:0] $end
$var reg 12 " buttons21[11:0] $end
$var reg 12 # buttons12[11:0] $end
$var reg 12 $ buttons13[11:0] $end
$var reg 12 % buttons23[11:0] $end
$var reg 12 & buttons33[11:0] $end
$var reg 1 ' latch $end
$var reg 1 ( clk $end
$var reg 1 ) data $end
$var reg 1 * clk_en $end
$var reg 1 + w_11_21 $end
$var reg 1 , endcol_11_21 $end
$var reg 1 - first_11_21 $end
$var reg 1 . latch_11_21 $end
$var reg 1 / clock_11_21 $end
$var reg 1 0 data_11_21 $end
$var reg 1 1 endrow_11_12 $end
$var reg 1 2 latch_11_12 $end
$var reg 1 3 clock_11_12 $end
$var reg 1 4 data_11_12 $end
$var reg 1 5 endrow_12_13 $end
$var reg 1 6 latch_12_13 $end
$var reg 1 7 clock_12_13 $end
$var reg 1 8 data_12_13 $end
$var reg 1 9 w_13_23 $end
$var reg 1 : endcol_13_23 $end
$var reg 1 ; first_13_23 $end
$var reg 1 < latch_13_23 $end
$var reg 1 = clock_13_23 $end
$var reg 1 > data_13_23 $end
$var reg 1 ? w_23_33 $end
$var reg 1 @ endcol_23_33 $end
$var reg 1 A first_23_33 $end
$var reg 1 B latch_23_33 $end
$var reg 1 C clock_23_33 $end
$var reg 1 D data_23_33 $end
$var reg 96 E sr_controllo[95:0] $end
$scope module uut11 $end
$var reg 12 F buttons[11:0] $end
$var reg 1 G t_w $end
$var reg 1 H t_endcol $end
$var reg 1 I t_first $end
$var reg 1 J t_latch $end
$var reg 1 K t_clk $end
$var reg 1 L t_data $end
$var reg 1 M b_w $end
$var reg 1 N b_endcol $end
$var reg 1 O b_first $end
$var reg 1 P b_latch $end
$var reg 1 Q b_clk $end
$var reg 1 R b_data $end
$var reg 1 S l_endrow $end
$var reg 1 T l_latch $end
$var reg 1 U l_clk $end
$var reg 1 V l_data $end
$var reg 1 W r_endrow $end
$var reg 1 X r_latch $end
$var reg 1 Y r_clk $end
$var reg 1 Z r_data $end
$var reg 1 [ latch $end
$var reg 1 \ clock $end
$var reg 1 ] data $end
$var reg 1 ^ nlatch $end
$var reg 1 _ ds_bridge $end
$var reg 1 ` ds_input $end
$var reg 1 a w_state $end
$var reg 6 b count_reg[5:0] $end
$var reg 6 c count[5:0] $end
$var reg 8 d sr2_inputs[7:0] $end
$var reg 1 e ffinput $end
$scope module sr1 $end
$var reg 1 f npl $end
$var reg 1 g nce $end
$var reg 1 h cp $end
$var reg 1 i ds $end
$var reg 8 j d[7:0] $end
$var reg 1 k q7 $end
$var reg 1 l nq7 $end
$var reg 8 m qs[7:0] $end
$upscope $end
$scope module sr2 $end
$var reg 1 n npl $end
$var reg 1 o nce $end
$var reg 1 p cp $end
$var reg 1 q ds $end
$var reg 8 r d[7:0] $end
$var reg 1 s q7 $end
$var reg 1 t nq7 $end
$var reg 8 u qs[7:0] $end
$upscope $end
$upscope $end
$scope module uut21 $end
$var reg 12 v buttons[11:0] $end
$var reg 1 w t_w $end
$var reg 1 x t_endcol $end
$var reg 1 y t_first $end
$var reg 1 z t_latch $end
$var reg 1 { t_clk $end
$var reg 1 | t_data $end
$var reg 1 } b_w $end
$var reg 1 !" b_endcol $end
$var reg 1 "" b_first $end
$var reg 1 #" b_latch $end
$var reg 1 $" b_clk $end
$var reg 1 %" b_data $end
$var reg 1 &" l_endrow $end
$var reg 1 '" l_latch $end
$var reg 1 (" l_clk $end
$var reg 1 )" l_data $end
$var reg 1 *" r_endrow $end
$var reg 1 +" r_latch $end
$var reg 1 ," r_clk $end
$var reg 1 -" r_data $end
$var reg 1 ." latch $end
$var reg 1 /" clock $end
$var reg 1 0" data $end
$var reg 1 1" nlatch $end
$var reg 1 2" ds_bridge $end
$var reg 1 3" ds_input $end
$var reg 1 4" w_state $end
$var reg 6 5" count_reg[5:0] $end
$var reg 6 6" count[5:0] $end
$var reg 8 7" sr2_inputs[7:0] $end
$var reg 1 8" ffinput $end
$scope module sr1 $end
$var reg 1 9" npl $end
$var reg 1 :" nce $end
$var reg 1 ;" cp $end
$var reg 1 <" ds $end
$var reg 8 =" d[7:0] $end
$var reg 1 >" q7 $end
$var reg 1 ?" nq7 $end
$var reg 8 @" qs[7:0] $end
$upscope $end
$scope module sr2 $end
$var reg 1 A" npl $end
$var reg 1 B" nce $end
$var reg 1 C" cp $end
$var reg 1 D" ds $end
$var reg 8 E" d[7:0] $end
$var reg 1 F" q7 $end
$var reg 1 G" nq7 $end
$var reg 8 H" qs[7:0] $end
$upscope $end
$upscope $end
$scope module uut12 $end
$var reg 12 I" buttons[11:0] $end
$var reg 1 J" t_w $end
$var reg 1 K" t_endcol $end
$var reg 1 L" t_first $end
$var reg 1 M" t_latch $end
$var reg 1 N" t_clk $end
$var reg 1 O" t_data $end
$var reg 1 P" b_w $end
$var reg 1 Q" b_endcol $end
$var reg 1 R" b_first $end
$var reg 1 S" b_latch $end
$var reg 1 T" b_clk $end
$var reg 1 U" b_data $end
$var reg 1 V" l_endrow $end
$var reg 1 W" l_latch $end
$var reg 1 X" l_clk $end
$var reg 1 Y" l_data $end
$var reg 1 Z" r_endrow $end
$var reg 1 [" r_latch $end
$var reg 1 \" r_clk $end
$var reg 1 ]" r_data $end
$var reg 1 ^" latch $end
$var reg 1 _" clock $end
$var reg 1 `" data $end
$var reg 1 a" nlatch $end
$var reg 1 b" ds_bridge $end
$var reg 1 c" ds_input $end
$var reg 1 d" w_state $end
$var reg 6 e" count_reg[5:0] $end
$var reg 6 f" count[5:0] $end
$var reg 8 g" sr2_inputs[7:0] $end
$var reg 1 h" ffinput $end
$scope module sr1 $end
$var reg 1 i" npl $end
$var reg 1 j" nce $end
$var reg 1 k" cp $end
$var reg 1 l" ds $end
$var reg 8 m" d[7:0] $end
$var reg 1 n" q7 $end
$var reg 1 o" nq7 $end
$var reg 8 p" qs[7:0] $end
$upscope $end
$scope module sr2 $end
$var reg 1 q" npl $end
$var reg 1 r" nce $end
$var reg 1 s" cp $end
$var reg 1 t" ds $end
$var reg 8 u" d[7:0] $end
$var reg 1 v" q7 $end
$var reg 1 w" nq7 $end
$var reg 8 x" qs[7:0] $end
$upscope $end
$upscope $end
$scope module uut13 $end
$var reg 12 y" buttons[11:0] $end
$var reg 1 z" t_w $end
$var reg 1 {" t_endcol $end
$var reg 1 |" t_first $end
$var reg 1 }" t_latch $end
$var reg 1 !# t_clk $end
$var reg 1 "# t_data $end
$var reg 1 ## b_w $end
$var reg 1 $# b_endcol $end
$var reg 1 %# b_first $end
$var reg 1 &# b_latch $end
$var reg 1 '# b_clk $end
$var reg 1 (# b_data $end
$var reg 1 )# l_endrow $end
$var reg 1 *# l_latch $end
$var reg 1 +# l_clk $end
$var reg 1 ,# l_data $end
$var reg 1 -# r_endrow $end
$var reg 1 .# r_latch $end
$var reg 1 /# r_clk $end
$var reg 1 0# r_data $end
$var reg 1 1# latch $end
$var reg 1 2# clock $end
$var reg 1 3# data $end
$var reg 1 4# nlatch $end
$var reg 1 5# ds_bridge $end
$var reg 1 6# ds_input $end
$var reg 1 7# w_state $end
$var reg 6 8# count_reg[5:0] $end
$var reg 6 9# count[5:0] $end
$var reg 8 :# sr2_inputs[7:0] $end
$var reg 1 ;# ffinput $end
$scope module sr1 $end
$var reg 1 <# npl $end
$var reg 1 =# nce $end
$var reg 1 ># cp $end
$var reg 1 ?# ds $end
$var reg 8 @# d[7:0] $end
$var reg 1 A# q7 $end
$var reg 1 B# nq7 $end
$var reg 8 C# qs[7:0] $end
$upscope $end
$scope module sr2 $end
$var reg 1 D# npl $end
$var reg 1 E# nce $end
$var reg 1 F# cp $end
$var reg 1 G# ds $end
$var reg 8 H# d[7:0] $end
$var reg 1 I# q7 $end
$var reg 1 J# nq7 $end
$var reg 8 K# qs[7:0] $end
$upscope $end
$upscope $end
$scope module uut23 $end
$var reg 12 L# buttons[11:0] $end
$var reg 1 M# t_w $end
$var reg 1 N# t_endcol $end
$var reg 1 O# t_first $end
$var reg 1 P# t_latch $end
$var reg 1 Q# t_clk $end
$var reg 1 R# t_data $end
$var reg 1 S# b_w $end
$var reg 1 T# b_endcol $end
$var reg 1 U# b_first $end
$var reg 1 V# b_latch $end
$var reg 1 W# b_clk $end
$var reg 1 X# b_data $end
$var reg 1 Y# l_endrow $end
$var reg 1 Z# l_latch $end
$var reg 1 [# l_clk $end
$var reg 1 \# l_data $end
$var reg 1 ]# r_endrow $end
$var reg 1 ^# r_latch $end
$var reg 1 _# r_clk $end
$var reg 1 `# r_data $end
$var reg 1 a# latch $end
$var reg 1 b# clock $end
$var reg 1 c# data $end
$var reg 1 d# nlatch $end
$var reg 1 e# ds_bridge $end
$var reg 1 f# ds_input $end
$var reg 1 g# w_state $end
$var reg 6 h# count_reg[5:0] $end
$var reg 6 i# count[5:0] $end
$var reg 8 j# sr2_inputs[7:0] $end
$var reg 1 k# ffinput $end
$scope module sr1 $end
$var reg 1 l# npl $end
$var reg 1 m# nce $end
$var reg 1 n# cp $end
$var reg 1 o# ds $end
$var reg 8 p# d[7:0] $end
$var reg 1 q# q7 $end
$var reg 1 r# nq7 $end
$var reg 8 s# qs[7:0] $end
$upscope $end
$scope module sr2 $end
$var reg 1 t# npl $end
$var reg 1 u# nce $end
$var reg 1 v# cp $end
$var reg 1 w# ds $end
$var reg 8 x# d[7:0] $end
$var reg 1 y# q7 $end
$var reg 1 z# nq7 $end
$var reg 8 {# qs[7:0] $end
$upscope $end
$upscope $end
$scope module uut33 $end
$var reg 12 |# buttons[11:0] $end
$var reg 1 }# t_w $end
$var reg 1 !$ t_endcol $end
$var reg 1 "$ t_first $end
$var reg 1 #$ t_latch $end
$var reg 1 $$ t_clk $end
$var reg 1 %$ t_data $end
$var reg 1 &$ b_w $end
$var reg 1 '$ b_endcol $end
$var reg 1 ($ b_first $end
$var reg 1 )$ b_latch $end
$var reg 1 *$ b_clk $end
$var reg 1 +$ b_data $end
$var reg 1 ,$ l_endrow $end
$var reg 1 -$ l_latch $end
$var reg 1 .$ l_clk $end
$var reg 1 /$ l_data $end
$var reg 1 0$ r_endrow $end
$var reg 1 1$ r_latch $end
$var reg 1 2$ r_clk $end
$var reg 1 3$ r_data $end
$var reg 1 4$ latch $end
$var reg 1 5$ clock $end
$var reg 1 6$ data $end
$var reg 1 7$ nlatch $end
$var reg 1 8$ ds_bridge $end
$var reg 1 9$ ds_input $end
$var reg 1 :$ w_state $end
$var reg 6 ;$ count_reg[5:0] $end
$var reg 6 <$ count[5:0] $end
$var reg 8 =$ sr2_inputs[7:0] $end
$var reg 1 >$ ffinput $end
$scope module sr1 $end
$var reg 1 ?$ npl $end
$var reg 1 @$ nce $end
$var reg 1 A$ cp $end
$var reg 1 B$ ds $end
$var reg 8 C$ d[7:0] $end
$var reg 1 D$ q7 $end
$var reg 1 E$ nq7 $end
$var reg 8 F$ qs[7:0] $end
$upscope $end
$scope module sr2 $end
$var reg 1 G$ npl $end
$var reg 1 H$ nce $end
$var reg 1 I$ cp $end
$var reg 1 J$ ds $end
$var reg 8 K$ d[7:0] $end
$var reg 1 L$ q7 $end
$var reg 1 M$ nq7 $end
$var reg 8 N$ qs[7:0] $end
$upscope $end
$upscope $end
$upscope $end
$enddefinitions $end
#0
b101101000100 !
b110000100011 "
b001101001101 #
b111000010001 $
b111101010101 %
b101010100001 &
1'
0(
1)
0*
0+
0,
0-
1.
0/
10
01
12
Z3
04
05
16
H7
18
09
0:
0;
1<
H=
1>
0?
0@
0A
1B
HC
1D
b000000000000000000000000000000000000000000000000000000000000000000000000000000000000000000000000 E
b101101000100 F
0G
0H
0I
1J
0K
1L
0M
0N
1O
0P
0Q
1R
0S
1T
ZU
0V
0W
1X
0Y
1Z
1[
0\
1]
0^
0_
1`
0a
b000000 b
b000000 c
b01001100 d
0e
0f
0g
0h
0i
b10110100 j
1k
0l
b10110100 m
0n
0o
0p
1q
b01001100 r
0s
1t
b01001100 u
b110000100011 v
1w
1x
0y
1z
0{
0|
0}
0!"
0""
1#"
0$"
1%"
1&"
1'"
Z("
0)"
0*"
0+"
0,"
1-"
1."
0/"
10"
01"
02"
03"
04"
b000000 5"
b000000 6"
b00111111 7"
08"
09"
0:"
0;"
0<"
b11000010 ="
1>"
0?"
b11000010 @"
0A"
0B"
0C"
0D"
b00111111 E"
0F"
1G"
b00111111 H"
b001101001101 I"
1J"
1K"
0L"
1M"
ZN"
0O"
0P"
0Q"
1R"
0S"
0T"
0U"
0V"
1W"
HX"
1Y"
0Z"
1["
Z\"
0]"
1^"
H_"
0`"
0a"
1b"
1c"
1d"
b000000 e"
b000000 f"
b11011101 g"
0h"
0i"
0j"
Hk"
1l"
b00110100 m"
0n"
1o"
b00110100 p"
0q"
0r"
Hs"
1t"
b11011101 u"
1v"
0w"
b11011101 x"
b111000010001 y"
0z"
0{"
0|"
1}"
H!#
1"#
0##
0$#
1%#
0&#
0'#
1(#
1)#
1*#
Z+#
0,#
0-#
1.#
H/#
10#
11#
H2#
13#
04#
05#
16#
07#
b000000 8#
b000000 9#
b00011110 :#
0;#
0<#
0=#
H>#
0?#
b11100001 @#
1A#
0B#
b11100001 C#
0D#
0E#
HF#
1G#
b00011110 H#
0I#
1J#
b00011110 K#
b111101010101 L#
0M#
0N#
0O#
1P#
HQ#
1R#
0S#
0T#
0U#
1V#
HW#
1X#
1Y#
1Z#
Z[#
0\#
0]#
0^#
0_#
1`#
1a#
Hb#
1c#
0d#
0e#
1f#
0g#
b000000 h#
b000000 i#
b01011110 j#
0k#
0l#
0m#
Hn#
0o#
b11110101 p#
1q#
0r#
b11110101 s#
0t#
0u#
Hv#
1w#
b01011110 x#
0y#
1z#
b01011110 {#
b101010100001 |#
1}#
1!$
0"$
1#$
H$$
0%$
0&$
0'$
0($
1)$
H*$
1+$
1,$
1-$
Z.$
0/$
00$
01$
02$
13$
14$
H5$
16$
07$
08$
09$
0:$
b000000 ;$
b000000 <$
b00011111 =$
0>$
0?$
0@$
HA$
0B$
b10101010 C$
1D$
0E$
b10101010 F$
0G$
0H$
HI$
0J$
b00011111 K$
0L$
1M$
b00011111 N$
#20000000
0'
0.
02
06
0<
0B
0J
0T
0X
0[
1^
1f
1n
0z
0#"
0'"
0."
11"
19"
1A"
0M"
0W"
0["
0^"
1a"
1i"
1q"
0}"
0*#
0.#
01#
14#
1<#
1D#
0P#
0V#
0Z#
0a#
1d#
1l#
1t#
0#$
0)$
0-$
04$
17$
1?$
1G$
#40000000
1*
#45000000
1(
0)
1/
b000000000000000000000000000000000000000000000000000000000000000000000000000000000000000000000001 E
1K
0R
1Y
0Z
1\
0]
1_
b000001 b
b000001 c
1h
1i
0k
1l
b01101000 m
1p
1s
0t
b10011001 u
1{
1$"
1/"
b000001 5"
b000001 6"
1;"
b10000100 @"
1C"
b01111110 H"
#50000000
0(
0/
0K
0Y
0\
0h
0p
0{
0$"
0/"
0;"
0C"
#55000000
1(
1)
1/
00
b000000000000000000000000000000000000000000000000000000000000000000000000000000000000000000000010 E
1K
0L
1R
1Y
1Z
1\
1]
0_
0`
b000010 b
b000010 c
1h
0i
1k
0l
b11010001 m
1p
0q
0s
1t
b00110011 u
1{
1$"
0%"
0-"
1/"
00"
12"
b000010 5"
b000010 6"
1;"
1<"
0>"
1?"
b00001000 @"
1C"
1F"
0G"
b11111100 H"
#60000000
0(
0/
0K
0Y
0\
0h
0p
0{
0$"
0/"
0;"
0C"
#65000000
1(
1/
b000000000000000000000000000000000000000000000000000000000000000000000000000000000000000000000101 E
1K
1Y
1\
b000011 b
b000011 c
1h
b10100010 m
1p
b01100110 u
1{
1$"
1/"
b000011 5"
b000011 6"
1;"
b00010001 @"
1C"
b11111000 H"
#70000000
0(
0/
0K
0Y
0\
0h
0p
0{
0$"
0/"
0;"
0C"
#75000000
1(
0)
1/
b000000000000000000000000000000000000000000000000000000000000000000000000000000000000000000001011 E
1K
0R
1Y
0Z
1\
0]
1_
b000100 b
b000100 c
1h
1i
0k
1l
b01000100 m
1p
1s
0t
b11001100 u
1{
1$"
1/"
b000100 5"
b000100 6"
1;"
b00100011 @"
1C"
b11110000 H"
#80000000
0(
0/
0K
0Y
0\
0h
0p
0{
0$"
0/"
0;"
0C"
#85000000
1(
1)
1/
b000000000000000000000000000000000000000000000000000000000000000000000000000000000000000000010110 E
1K
1R
1Y
1Z
1\
1]
b000101 b
b000101 c
1h
1k
0l
b10001001 m
1p
b10011000 u
1{
1$"
1/"
b000101 5"
b000101 6"
1;"
b01000111 @"
1C"
b11100000 H"
#90000000
0(
0/
0K
0Y
0\
0h
0p
0{
0$"
0/"
0;"
0C"
#95000000
1(
0)
1/
10
b000000000000000000000000000000000000000000000000000000000000000000000000000000000000000000101101 E
1K
1L
0R
1Y
0Z
1\
0]
0_
1`
b000110 b
b000110 c
1h
0i
0k
1l
b00010011 m
1p
1q
0s
1t
b00110000 u
1{
1$"
1%"
1-"
1/"
10"
b000110 5"
b000110 6"
1;"
1>"
0?"
b10001111 @"
1C"
b11000000 H"
#100000000
0(
0/
0K
0Y
0\
0h
0p
0{
0$"
0/"
0;"
0C"
#105000000
1(
1/
00
b000000000000000000000000000000000000000000000000000000000000000000000000000000000000000001011010 E
1K
0L
1Y
1\
0`
b000111 b
b000111 c
1h
b00100110 m
1p
0q
b01100001 u
1{
1$"
0%"
0-"
1/"
00"
b000111 5"
b000111 6"
1;"
0>"
1?"
b00011111 @"
1C"
b10000000 H"
#110000000
0(
0/
0K
0Y
0\
0h
0p
0{
0$"
0/"
0;"
0C"
#115000000
1(
1/
b000000000000000000000000000000000000000000000000000000000000000000000000000000000000000010110100 E
1K
1Y
1\
1_
b001000 b
b001000 c
1h
1i
b01001100 m
1p
1s
0t
b11000010 u
1{
1$"
1/"
02"
b001000 5"
b001000 6"
1;"
0<"
b00111111 @"
1C"
0F"
1G"
b00000000 H"
#120000000
0(
0/
0K
0Y
0\
0h
0p
0{
0$"
0/"
0;"
0C"
#125000000
1(
1)
1/
b000000000000000000000000000000000000000000000000000000000000000000000000000000000000000101101000 E
1K
1R
1Y
1Z
1\
1]
b001001 b
b001001 c
1h
1k
0l
b10011001 m
1p
b10000100 u
1{
1$"
1/"
b001001 5"
b001001 6"
1;"
b01111110 @"
1C"
#130000000
0(
0/
0K
0Y
0\
0h
0p
0{
0$"
0/"
0;"
0C"
#135000000
1(
0)
1/
10
b000000000000000000000000000000000000000000000000000000000000000000000000000000000000001011010001 E
1K
1L
0R
1Y
0Z
1\
0]
0_
1`
b001010 b
b001010 c
1h
0i
0k
1l
b00110011 m
1p
1q
0s
1t
b00001000 u
1{
1$"
1%"
1-"
1/"
10"
b001010 5"
b001010 6"
1;"
1>"
0?"
b11111100 @"
1C"
#140000000
0(
0/
0K
0Y
0\
0h
0p
0{
0$"
0/"
0;"
0C"
#145000000
1(
1/
b000000000000000000000000000000000000000000000000000000000000000000000000000000000000010110100010 E
1K
1Y
1\
b001011 b
b001011 c
1h
b01100110 m
1p
b00010001 u
1{
1$"
1/"
b001011 5"
b001011 6"
1;"
b11111000 @"
1C"
#150000000
0(
0/
0K
0Y
0\
0h
0p
0{
0$"
0/"
0;"
0C"
#155000000
1(
1)
1/
b000000000000000000000000000000000000000000000000000000000000000000000000000000000000101101000100 E
1K
1R
1Y
1Z
1\
1]
b001100 b
b001100 c
1h
1k
0l
b11001100 m
1p
b00100011 u
1{
1$"
1/"
b001100 5"
b001100 6"
1;"
b11110000 @"
1C"
#160000000
0(
0/
0K
0Y
0\
0h
0p
0{
0$"
0/"
0;"
0C"
#165000000
1(
1/
b000000000000000000000000000000000000000000000000000000000000000000000000000000000001011010001001 E
1K
1Y
1\
b001101 b
b001101 c
1h
b10011000 m
1p
b01000111 u
1{
1$"
1/"
b001101 5"
b001101 6"
1;"
b11100000 @"
1C"
#170000000
0(
0/
0K
0Y
0\
0h
0p
0{
0$"
0/"
0;"
0C"
#175000000
1(
0)
1/
b000000000000000000000000000000000000000000000000000000000000000000000000000000000010110100010011 E
1K
0R
1Y
0Z
1\
0]
1_
b001110 b
b001110 c
1h
1i
0k
1l
b00110000 m
1p
1s
0t
b10001111 u
1{
1$"
1/"
b001110 5"
b001110 6"
1;"
b11000000 @"
1C"
#180000000
0(
0/
0K
0Y
0\
0h
0p
0{
0$"
0/"
0;"
0C"
