hardware/simulation/74hc165.vhdl
library IEEE;
use IEEE.std_logic_1164.all;

entity T74HCT165 is
port (
    nPL                 : IN  std_logic;
    nCE                : IN  std_logic;
    CP                  : IN  std_logic;
    DS                  : IN  std_logic;
    D                    : IN  std_logic_vector(7 downto 0);
    Q7                  : OUT std_logic;
    nQ7                : OUT std_logic
);
end T74HCT165;

architecture behave_T74HCT165 of T74HCT165 is
signal  Qs            : std_logic_vector(7 downto 0) ;

begin
HCT165 : process(nPL, CP, D)
begin
    if(nPL = '0') then
        Qs <= D;
    elsif(CP'event and CP = '1') then
        if(nCE = '0') then
            Qs <= Qs(6 downto 0) & DS;    -- or  Qs <= shl(Qs, '1') & DS;
        end if;
    end if;
end process;
    Q7 <= Qs(7);
    nQ7 <= not(Qs(7));
end behave_T74HCT165;

hardware/simulation/tile.vhdl
library ieee;
use ieee.std_logic_1164.all;
use IEEE.NUMERIC_STD.ALL;

entity tile is
  port (
    buttons : in std_logic_vector(11 downto 0) := (others => 'L');

    T_W : in std_logic := 'Z';
    T_endcol : in std_logic := 'Z';
    T_first : out std_logic := '0';
    T_latch : out std_logic;
    T_clk : out std_logic;
    T_data : in std_logic := 'Z';

    B_W : out std_logic;
    B_endcol : out std_logic := '0';
    B_first : in std_logic := 'Z';
    B_latch : in std_logic := 'Z';
    B_clk : in std_logic := 'Z';
    B_data : out std_logic;

    L_endrow : in std_logic := 'Z';
    L_latch : out std_logic;
    L_clk : out std_logic;
    L_data : in std_logic := 'Z';

    R_endrow : out std_logic := '0';
    R_latch : in std_logic := 'Z';
    R_clk : in std_logic := 'Z';
    R_data : out std_logic
  );
end tile;

architecture rtl of tile is

signal latch, clock, data : std_logic; -- sengnali principali
signal nlatch : std_logic;

signal ds_bridge : std_logic; -- sengale per connettere l'uscita seriale di SR2 a SR1
signal ds_input : std_logic; -- ds in input dai moduli adiacenti

signal w_state : std_logic; -- stato dei buffer 3state

signal count_reg : unsigned(5 downto 0) := (others => '0'); -- contatore
signal count : std_logic_vector(5 downto 0);

signal sr2_inputs : std_logic_vector(7 downto 0); -- Segnale di supporto
signal ffinput : std_logic;

signal T_W_p, T_endcol_p, T_data_p, B_first_p, B_latch_p, B_clk_p, L_endrow_p, L_data_p, R_latch_p, R_clk_p : std_logic;

begin

  -- input pullups / pulldowns
  T_W_p       <= 'H';
  T_endcol_p  <= 'H';
  T_data_p    <= 'L';
  B_first_p   <= 'H';
  B_latch_p   <= 'L';
  B_clk_p     <= 'H';
  L_endrow_p  <= 'H';
  L_data_p    <= 'L';
  R_latch_p   <= 'L';
  R_clk_p     <= 'H';

  T_W_p       <=   T_W;
  T_endcol_p  <=   T_endcol;
  T_data_p    <=   T_data;
  B_first_p   <=   B_first;
  B_latch_p   <=   B_latch;
  B_clk_p     <=   B_clk;
  L_endrow_p  <=   L_endrow;
  L_data_p    <=   L_data;
  R_latch_p   <=   R_latch;
  R_clk_p     <=   R_clk;


  -- inputs wiring
  clock <= R_clk_p;
  clock <= B_clk_p;

  w_state <= T_W_p and B_first_p;

  latch <= R_latch_p or B_latch_p;  -- il latch è come un reset quindi lo mettiamo in or
  ds_input <= T_data_p when to_x01(w_state) = '0' else L_data_p;


  -- outputs wiring
  R_data <= data;
  B_data <= data;

  T_latch <= latch;
  L_latch <= latch;

  T_clk <= clock when to_x01(w_state) = '0' else 'Z';
  L_clk <= clock when to_x01(w_state) = '1' else 'Z';



  nlatch <= not latch;



  -- sr LSB
  sr1 : entity work.T74HCT165
    port map(
      nPL => nlatch,
      nCE => '0',
      CP => clock,
      DS => ds_bridge,
      D => buttons(11 downto 4),
      Q7 => data,
      nQ7 => open
    );

  sr2_inputs <= buttons(3 downto 0) & "11" & to_x01(L_endrow_p) & to_x01(T_endcol_p);

  -- sr MSB
  sr2 : entity work.T74HCT165
    port map(
      nPL => nlatch,
      nCE => '0',
      CP => clock,
      DS => ds_input,
      D => sr2_inputs,
      Q7 => ds_bridge,
      nQ7 => open
    );



  process(clock, latch)
  begin
    if latch = '1' then
      count_reg <= (others => '0');
    elsif rising_edge(clock) then
      count_reg <= count_reg + 1;
    end if;
  end process;

  count <= std_logic_vector(count_reg);
  ffinput <= count(3) and count(2) and count(1) and count(0) and data;

  process(clock, latch)
  begin
    if latch = '1' then
      B_W <= '0';
    elsif rising_edge(clock) then
      if ffinput = '1' then
        B_W <= '1';
      end if;
    end if;
  end process;


end rtl;

hardware/simulation/tile_tb.vhdl
library ieee;
use ieee.std_logic_1164.all;
use ieee.numeric_std.all;

entity tile_tb is
end tile_tb;

architecture sim of tile_tb is

  signal buttons11    : std_logic_vector(11 downto 0);
  signal buttons21    : std_logic_vector(11 downto 0);
  signal buttons12    : std_logic_vector(11 downto 0);
  signal buttons13    : std_logic_vector(11 downto 0);
  signal buttons23    : std_logic_vector(11 downto 0);
  signal buttons33    : std_logic_vector(11 downto 0);

  signal latch, clk, data : std_logic;

  constant CLK_PERIOD : time := 10 ns;

  signal clk_en : std_logic := '0';

  -- signals between tile 11 and tile 21
  signal W_11_21, endcol_11_21, first_11_21, latch_11_21, clock_11_21, data_11_21 : std_logic;
  -- signals between tile 11 and tile 12
  signal endrow_11_12, latch_11_12, clock_11_12, data_11_12 : std_logic;
  -- signals between tile 12 and tile 13
  signal endrow_12_13, latch_12_13, clock_12_13, data_12_13 : std_logic;
  -- signals between tile 13 and tile 23
  signal W_13_23, endcol_13_23, first_13_23, latch_13_23, clock_13_23, data_13_23 : std_logic;
  -- signals between tile 23 and tile 33
  signal W_23_33, endcol_23_33, first_23_33, latch_23_33, clock_23_33, data_23_33 : std_logic;


  signal sr_controllo : std_logic_vector(95 downto 0) := (others => '0');

begin

    -- Tile instances
    uut11: entity work.tile
        port map (
            buttons => buttons11,
            T_W => W_11_21,
            T_endcol => endcol_11_21,
            T_first => first_11_21,
            T_latch => latch_11_21,
            T_clk => clock_11_21,
            t_data => data_11_21,
            B_W => open,
            B_endcol => open,
            B_data => open,
            L_endrow => endrow_11_12,
            L_latch => latch_11_12,
            L_clk => clock_11_12,
            L_data => data_11_12,
            R_endrow => open,
            R_latch => latch,
            R_clk => clk,
            R_data => data
        );

    uut21: entity work.tile
        port map (
            buttons => buttons21,
            T_first => open,
            T_latch => open,
            T_clk => open,
            B_W => W_11_21,
            B_endcol => endcol_11_21,
            B_first => first_11_21,
            B_latch => latch_11_21,
            B_clk => clock_11_21,
            B_data => data_11_21,
            L_latch => open,
            L_clk => open,
            R_endrow => open,
            R_data => open
        );

    uut12: entity work.tile
        port map (
            buttons => buttons12,
            T_first => open,
            T_latch => open,
            T_clk => open,
            B_W => open,
            B_endcol => open,
            B_data => open,
            L_endrow => endrow_12_13,
            L_latch => latch_12_13,
            L_clk => clock_12_13,
            L_data => data_12_13,
            R_endrow => endrow_11_12,
            R_data => data_11_12,
            R_clk => clock_11_12,
            R_latch => latch_11_12
        );

    uut13: entity work.tile
        port map (
            buttons => buttons13,
            T_W => W_13_23,
            T_endcol => endcol_13_23,
            T_first => first_13_23,
            T_latch => latch_13_23,
            T_clk => clock_13_23,
            T_data => data_13_23,
            B_W => open,
            B_endcol => open,
            B_data => open,
            L_latch => open,
            L_clk => open,
            R_endrow => endrow_12_13,
            R_data => data_12_13,
            R_clk => clock_12_13,
            R_latch => latch_12_13
        );

    uut23: entity work.tile
        port map (
            buttons => buttons23,
            T_W => W_23_33,
            T_endcol => endcol_23_33,
            T_first => first_23_33,
            T_latch => latch_23_33,
            T_clk => clock_23_33,
            T_data => data_23_33,
            B_W => W_13_23,
            B_endcol => endcol_13_23,
            B_first => first_13_23,
            B_data => data_13_23,
            B_latch => latch_13_23,
            B_clk => clock_13_23,
            L_latch => open,
            L_clk => open,
            R_endrow => open,
            R_data => open
        );

    uut33: entity work.tile
        port map (
            buttons => buttons33,
            T_first => open,
            T_latch => open,
            T_clk => open,
            B_W => W_23_33,
            B_endcol => endcol_23_33,
            B_first => first_23_33,
            B_latch => latch_23_33,
            B_clk => clock_23_33,
            B_data => data_23_33,
            L_latch => open,
            L_clk => open,
            R_endrow => open,
            R_data => open
        );

    -- Clock generator (on the R_clk line)
    clk_process : process  -- gated by clk_en
    begin
        while true loop
            if clk_en = '1' then
                clk <= '0';
                wait for CLK_PERIOD/2;
                clk <= '1';
                wait for CLK_PERIOD/2;
            else
                clk <= '0';
                -- Important: when the clock is disabled we must
                -- wait for clk_en to change, otherwise the loop spins
                -- forever at the same simulation time (hang).
                wait until clk_en = '1';
            end if;
        end loop;
        wait; -- stop everything
    end process;



    capture_data: process(clk)
    begin
        if rising_edge(clk) then
            if latch = '0' then
                -- shift left: the new bit enters at position 0
                sr_controllo <= sr_controllo(94 downto 0) & data;
            end if;
        end if;
    end process;



    -- Main stimulus
    stim_proc: process
    begin

        buttons11 <= x"B44";
        buttons21 <= x"C23";
        buttons12 <= x"34D";
        buttons13 <= x"E11";
        buttons23 <= x"F55";
        buttons33 <= x"AA1";

        latch <= '1';  -- parallel load (latch)
        wait for 20 ns;
        latch <= '0'; -- shifting
        wait for 20 ns;

        clk_en <= '1';
        wait for CLK_PERIOD * 95;
        clk_en <= '0';

        wait for 40 ns;




        buttons11 <= x"DF3";
        buttons21 <= x"A31";
        buttons12 <= x"000";
        buttons13 <= x"FFF";
        buttons23 <= x"A34";
        buttons33 <= x"843";

        latch <= '1';  -- parallel load (latch)
        wait for 20 ns;
        latch <= '0'; -- shifting
        wait for 20 ns;

        clk_en <= '1';
        wait for CLK_PERIOD * 95;
        clk_en <= '0';

        wait for 40 ns;


        --wait for CLK_PERIOD * 2;
        wait;
    end process;

end sim;

hardware/simulation/tile.vcd
$date
  Thu Jan  8 20:50:08 2026
$end
$version
  GHDL v0
$end
$timescale
  1 fs
$end
$scope module standard $end
$upscope $end
$scope module std_logic_1164 $end
$upscope $end
$scope module numeric_std $end
$upscope $end
$scope module tile_tb $end
$var reg 12 ! buttons11[11:0] $end
$var reg 12 " buttons21[11:0] $end
$var reg 12 # buttons12[11:0] $end
$var reg 12 $ buttons13[11:0] $end
$var reg 12 % buttons23[11:0] $end
$var reg 12 & buttons33[11:0] $end
$var reg 1 ' latch $end
$var reg 1 ( clk $end
$var reg 1 ) data $end
$var reg 1 * clk_en $end
$var reg 1 + w_11_21 $end
$var reg 1 , endcol_11_21 $end
$var reg 1 - first_11_21 $end
$var reg 1 . latch_11_21 $end
$var reg 1 / clock_11_21 $end
$var reg 1 0 data_11_21 $end
$var reg 1 1 endrow_11_12 $end
$var reg 1 2 latch_11_12 $end
$var reg 1 3 clock_11_12 $end
$var reg 1 4 data_11_12 $end
$var reg 1 5 endrow_12_13 $end
$var reg 1 6 latch_12_13 $end
$var reg 1 7 clock_12_13 $end
$var reg 1 8 data_12_13 $end
$var reg 1 9 w_13_23 $end
$var reg 1 : endcol_13_23 $end
$var reg 1 ; first_13_23 $end
$var reg 1 < latch_13_23 $end
$var reg 1 = clock_13_23 $end
$var reg 1 > data_13_23 $end
$var reg 1 ? w_23_33 $end
$var reg 1 @ endcol_23_33 $end
$var reg 1 A first_23_33 $end
$var reg 1 B latch_23_33 $end
$var reg 1 C clock_23_33 $end
$var reg 1 D data_23_33 $end
$var reg 96 E sr_controllo[95:0] $end
$scope module uut11 $end
$var reg 12 F buttons[11:0] $end
$var reg 1 G t_w $end
$var reg 1 H t_endcol $end
$var reg 1 I t_first $end
$var reg 1 J t_latch $end
$var reg 1 K t_clk $end
$var reg 1 L t_data $end
$var reg 1 M b_w $end
$var reg 1 N b_endcol $end
$var reg 1 O b_first $end
$var reg 1 P b_latch $end
$var reg 1 Q b_clk $end
$var reg 1 R b_data $end
$var reg 1 S l_endrow $end
$var reg 1 T l_latch $end
$var reg 1 U l_clk $end
$var reg 1 V l_data $end
$var reg 1 W r_endrow $end
$var reg 1 X r_latch $end
$var reg 1 Y r_clk $end
$var reg 1 Z r_data $end
$var reg 1 [ latch $end
$var reg 1 \ clock $end
$var reg 1 ] data $end
$var reg 1 ^ nlatch $end
$var reg 1 _ ds_bridge $end
$var reg 1 ` ds_input $end
$var reg 1 a w_state $end
$var reg 6 b count_reg[5:0] $end
$var reg 6 c count[5:0] $end
$var reg 8 d sr2_inputs[7:0] $end
$var reg 1 e ffinput $end
$var reg 1 f t_w_p $end
$var reg 1 g t_endcol_p $end
$var reg 1 h t_data_p $end
$var reg 1 i b_first_p $end
$var reg 1 j b_latch_p $end
$var reg 1 k b_clk_p $end
$var reg 1 l l_endrow_p $end
$var reg 1 m l_data_p $end
$var reg 1 n r_latch_p $end
$var reg 1 o r_clk_p $end
$scope module sr1 $end
$var reg 1 p npl $end
$var reg 1 q nce $end
$var reg 1 r cp $end
$var reg 1 s ds $end
$var reg 8 t d[7:0] $end
$var reg 1 u q7 $end
$var reg 1 v nq7 $end
$var reg 8 w qs[7:0] $end
$upscope $end
$scope module sr2 $end
$var reg 1 x npl $end
$var reg 1 y nce $end
$var reg 1 z cp $end
$var reg 1 { ds $end
$var reg 8 | d[7:0] $end
$var reg 1 } q7 $end
$var reg 1 !" nq7 $end
$var reg 8 "" qs[7:0] $end
$upscope $end
$upscope $end
$scope module uut21 $end
$var reg 12 #" buttons[11:0] $end
$var reg 1 $" t_w $end
$var reg 1 %" t_endcol $end
$var reg 1 &" t_first $end
$var reg 1 '" t_latch $end
$var reg 1 (" t_clk $end
$var reg 1 )" t_data $end
$var reg 1 *" b_w $end
$var reg 1 +" b_endcol $end
$var reg 1 ," b_first $end
$var reg 1 -" b_latch $end
$var reg 1 ." b_clk $end
$var reg 1 /" b_data $end
$var reg 1 0" l_endrow $end
$var reg 1 1" l_latch $end
$var reg 1 2" l_clk $end
$var reg 1 3" l_data $end
$var reg 1 4" r_endrow $end
$var reg 1 5" r_latch $end
$var reg 1 6" r_clk $end
$var reg 1 7" r_data $end
$var reg 1 8" latch $end
$var reg 1 9" clock $end
$var reg 1 :" data $end
$var reg 1 ;" nlatch $end
$var reg 1 <" ds_bridge $end
$var reg 1 =" ds_input $end
$var reg 1 >" w_state $end
$var reg 6 ?" count_reg[5:0] $end
$var reg 6 @" count[5:0] $end
$var reg 8 A" sr2_inputs[7:0] $end
$var reg 1 B" ffinput $end
$var reg 1 C" t_w_p $end
$var reg 1 D" t_endcol_p $end
$var reg 1 E" t_data_p $end
$var reg 1 F" b_first_p $end
$var reg 1 G" b_latch_p $end
$var reg 1 H" b_clk_p $end
$var reg 1 I" l_endrow_p $end
$var reg 1 J" l_data_p $end
$var reg 1 K" r_latch_p $end
$var reg 1 L" r_clk_p $end
$scope module sr1 $end
$var reg 1 M" npl $end
$var reg 1 N" nce $end
$var reg 1 O" cp $end
$var reg 1 P" ds $end
$var reg 8 Q" d[7:0] $end
$var reg 1 R" q7 $end
$var reg 1 S" nq7 $end
$var reg 8 T" qs[7:0] $end
$upscope $end
$scope module sr2 $end
$var reg 1 U" npl $end
$var reg 1 V" nce $end
$var reg 1 W" cp $end
$var reg 1 X" ds $end
$var reg 8 Y" d[7:0] $end
$var reg 1 Z" q7 $end
$var reg 1 [" nq7 $end
$var reg 8 \" qs[7:0] $end
$upscope $end
$upscope $end
$scope module uut12 $end
$var reg 12 ]" buttons[11:0] $end
$var reg 1 ^" t_w $end
$var reg 1 _" t_endcol $end
$var reg 1 `" t_first $end
$var reg 1 a" t_latch $end
$var reg 1 b" t_clk $end
$var reg 1 c" t_data $end
$var reg 1 d" b_w $end
$var reg 1 e" b_endcol $end
$var reg 1 f" b_first $end
$var reg 1 g" b_latch $end
$var reg 1 h" b_clk $end
$var reg 1 i" b_data $end
$var reg 1 j" l_endrow $end
$var reg 1 k" l_latch $end
$var reg 1 l" l_clk $end
$var reg 1 m" l_data $end
$var reg 1 n" r_endrow $end
$var reg 1 o" r_latch $end
$var reg 1 p" r_clk $end
$var reg 1 q" r_data $end
$var reg 1 r" latch $end
$var reg 1 s" clock $end
$var reg 1 t" data $end
$var reg 1 u" nlatch $end
$var reg 1 v" ds_bridge $end
$var reg 1 w" ds_input $end
$var reg 1 x" w_state $end
$var reg 6 y" count_reg[5:0] $end
$var reg 6 z" count[5:0] $end
$var reg 8 {" sr2_inputs[7:0] $end
$var reg 1 |" ffinput $end
$var reg 1 }" t_w_p $end
$var reg 1 !# t_endcol_p $end
$var reg 1 "# t_data_p $end
$var reg 1 ## b_first_p $end
$var reg 1 $# b_latch_p $end
$var reg 1 %# b_clk_p $end
$var reg 1 &# l_endrow_p $end
$var reg 1 '# l_data_p $end
$var reg 1 (# r_latch_p $end
$var reg 1 )# r_clk_p $end
$scope module sr1 $end
$var reg 1 *# npl $end
$var reg 1 +# nce $end
$var reg 1 ,# cp $end
$var reg 1 -# ds $end
$var reg 8 .# d[7:0] $end
$var reg 1 /# q7 $end
$var reg 1 0# nq7 $end
$var reg 8 1# qs[7:0] $end
$upscope $end
$scope module sr2 $end
$var reg 1 2# npl $end
$var reg 1 3# nce $end
$var reg 1 4# cp $end
$var reg 1 5# ds $end
$var reg 8 6# d[7:0] $end
$var reg 1 7# q7 $end
$var reg 1 8# nq7 $end
$var reg 8 9# qs[7:0] $end
$upscope $end
$upscope $end
$scope module uut13 $end
$var reg 12 :# buttons[11:0] $end
$var reg 1 ;# t_w $end
$var reg 1 <# t_endcol $end
$var reg 1 =# t_first $end
$var reg 1 ># t_latch $end
$var reg 1 ?# t_clk $end
$var reg 1 @# t_data $end
$var reg 1 A# b_w $end
$var reg 1 B# b_endcol $end
$var reg 1 C# b_first $end
$var reg 1 D# b_latch $end
$var reg 1 E# b_clk $end
$var reg 1 F# b_data $end
$var reg 1 G# l_endrow $end
$var reg 1 H# l_latch $end
$var reg 1 I# l_clk $end
$var reg 1 J# l_data $end
$var reg 1 K# r_endrow $end
$var reg 1 L# r_latch $end
$var reg 1 M# r_clk $end
$var reg 1 N# r_data $end
$var reg 1 O# latch $end
$var reg 1 P# clock $end
$var reg 1 Q# data $end
$var reg 1 R# nlatch $end
$var reg 1 S# ds_bridge $end
$var reg 1 T# ds_input $end
$var reg 1 U# w_state $end
$var reg 6 V# count_reg[5:0] $end
$var reg 6 W# count[5:0] $end
$var reg 8 X# sr2_inputs[7:0] $end
$var reg 1 Y# ffinput $end
$var reg 1 Z# t_w_p $end
$var reg 1 [# t_endcol_p $end
$var reg 1 \# t_data_p $end
$var reg 1 ]# b_first_p $end
$var reg 1 ^# b_latch_p $end
$var reg 1 _# b_clk_p $end
$var reg 1 `# l_endrow_p $end
$var reg 1 a# l_data_p $end
$var reg 1 b# r_latch_p $end
$var reg 1 c# r_clk_p $end
$scope module sr1 $end
$var reg 1 d# npl $end
$var reg 1 e# nce $end
$var reg 1 f# cp $end
$var reg 1 g# ds $end
$var reg 8 h# d[7:0] $end
$var reg 1 i# q7 $end
$var reg 1 j# nq7 $end
$var reg 8 k# qs[7:0] $end
$upscope $end
$scope module sr2 $end
$var reg 1 l# npl $end
$var reg 1 m# nce $end
$var reg 1 n# cp $end
$var reg 1 o# ds $end
$var reg 8 p# d[7:0] $end
$var reg 1 q# q7 $end
$var reg 1 r# nq7 $end
$var reg 8 s# qs[7:0] $end
$upscope $end
$upscope $end
$scope module uut23 $end
$var reg 12 t# buttons[11:0] $end
$var reg 1 u# t_w $end
$var reg 1 v# t_endcol $end
$var reg 1 w# t_first $end
$var reg 1 x# t_latch $end
$var reg 1 y# t_clk $end
$var reg 1 z# t_data $end
$var reg 1 {# b_w $end
$var reg 1 |# b_endcol $end
$var reg 1 }# b_first $end
$var reg 1 !$ b_latch $end
$var reg 1 "$ b_clk $end
$var reg 1 #$ b_data $end
$var reg 1 $$ l_endrow $end
$var reg 1 %$ l_latch $end
$var reg 1 &$ l_clk $end
$var reg 1 '$ l_data $end
$var reg 1 ($ r_endrow $end
$var reg 1 )$ r_latch $end
$var reg 1 *$ r_clk $end
$var reg 1 +$ r_data $end
$var reg 1 ,$ latch $end
$var reg 1 -$ clock $end
$var reg 1 .$ data $end
$var reg 1 /$ nlatch $end
$var reg 1 0$ ds_bridge $end
$var reg 1 1$ ds_input $end
$var reg 1 2$ w_state $end
$var reg 6 3$ count_reg[5:0] $end
$var reg 6 4$ count[5:0] $end
$var reg 8 5$ sr2_inputs[7:0] $end
$var reg 1 6$ ffinput $end
$var reg 1 7$ t_w_p $end
$var reg 1 8$ t_endcol_p $end
$var reg 1 9$ t_data_p $end
$var reg 1 :$ b_first_p $end
$var reg 1 ;$ b_latch_p $end
$var reg 1 <$ b_clk_p $end
$var reg 1 =$ l_endrow_p $end
$var reg 1 >$ l_data_p $end
$var reg 1 ?$ r_latch_p $end
$var reg 1 @$ r_clk_p $end
$scope module sr1 $end
$var reg 1 A$ npl $end
$var reg 1 B$ nce $end
$var reg 1 C$ cp $end
$var reg 1 D$ ds $end
$var reg 8 E$ d[7:0] $end
$var reg 1 F$ q7 $end
$var reg 1 G$ nq7 $end
$var reg 8 H$ qs[7:0] $end
$upscope $end
$scope module sr2 $end
$var reg 1 I$ npl $end
$var reg 1 J$ nce $end
$var reg 1 K$ cp $end
$var reg 1 L$ ds $end
$var reg 8 M$ d[7:0] $end
$var reg 1 N$ q7 $end
$var reg 1 O$ nq7 $end
$var reg 8 P$ qs[7:0] $end
$upscope $end
$upscope $end
$scope module uut33 $end
$var reg 12 Q$ buttons[11:0] $end
$var reg 1 R$ t_w $end
$var reg 1 S$ t_endcol $end
$var reg 1 T$ t_first $end
$var reg 1 U$ t_latch $end
$var reg 1 V$ t_clk $end
$var reg 1 W$ t_data $end
$var reg 1 X$ b_w $end
$var reg 1 Y$ b_endcol $end
$var reg 1 Z$ b_first $end
$var reg 1 [$ b_latch $end
$var reg 1 \$ b_clk $end
$var reg 1 ]$ b_data $end
$var reg 1 ^$ l_endrow $end
$var reg 1 _$ l_latch $end
$var reg 1 `$ l_clk $end
$var reg 1 a$ l_data $end
$var reg 1 b$ r_endrow $end
$var reg 1 c$ r_latch $end
$var reg 1 d$ r_clk $end
$var reg 1 e$ r_data $end
$var reg 1 f$ latch $end
$var reg 1 g$ clock $end
$var reg 1 h$ data $end
$var reg 1 i$ nlatch $end
$var reg 1 j$ ds_bridge $end
$var reg 1 k$ ds_input $end
$var reg 1 l$ w_state $end
$var reg 6 m$ count_reg[5:0] $end
$var reg 6 n$ count[5:0] $end
$var reg 8 o$ sr2_inputs[7:0] $end
$var reg 1 p$ ffinput $end
$var reg 1 q$ t_w_p $end
$var reg 1 r$ t_endcol_p $end
$var reg 1 s$ t_data_p $end
$var reg 1 t$ b_first_p $end
$var reg 1 u$ b_latch_p $end
$var reg 1 v$ b_clk_p $end
$var reg 1 w$ l_endrow_p $end
$var reg 1 x$ l_data_p $end
$var reg 1 y$ r_latch_p $end
$var reg 1 z$ r_clk_p $end
$scope module sr1 $end
$var reg 1 {$ npl $end
$var reg 1 |$ nce $end
$var reg 1 }$ cp $end
$var reg 1 !% ds $end
$var reg 8 "% d[7:0] $end
$var reg 1 #% q7 $end
$var reg 1 $% nq7 $end
$var reg 8 %% qs[7:0] $end
$upscope $end
$scope module sr2 $end
$var reg 1 &% npl $end
$var reg 1 '% nce $end
$var reg 1 (% cp $end
$var reg 1 )% ds $end
$var reg 8 *% d[7:0] $end
$var reg 1 +% q7 $end
$var reg 1 ,% nq7 $end
$var reg 8 -% qs[7:0] $end
$upscope $end
$upscope $end
$upscope $end
$enddefinitions $end
#0
b101101000100 !
b110000100011 "
b001101001101 #
b111000010001 $
b111101010101 %
b101010100001 &
1'
0(
1)
0*
0+
0,
0-
1.
0/
10
01
12
Z3
04
05
16
H7
18
09
0:
0;
1<
H=
1>
0?
0@
0A
1B
HC
1D
b000000000000000000000000000000000000000000000000000000000000000000000000000000000000000000000000 E
b101101000100 F
0G
0H
0I
1J
0K
1L
0M
0N
ZO
ZP
ZQ
1R
0S
1T
ZU
0V
0W
1X
0Y
1Z
1[
0\
1]
0^
0_
1`
0a
b000000 b
b000000 c
b01001100 d
0e
0f
0g
1h
Hi
Lj
Hk
0l
0m
1n
0o
0p
0q
0r
0s
b10110100 t
1u
0v
b10110100 w
0x
0y
0z
1{
b01001100 |
0}
1!"
b01001100 ""
b110000100011 #"
Z$"
Z%"
0&"
1'"
0("
Z)"
0*"
0+"
0,"
1-"
0."
1/"
Z0"
11"
Z2"
Z3"
04"
Z5"
Z6"
17"
18"
09"
1:"
0;"
0<"
L="
0>"
b000000 ?"
b000000 @"
b00111111 A"
0B"
HC"
HD"
LE"
0F"
1G"
0H"
HI"
LJ"
LK"
HL"
0M"
0N"
0O"
0P"
b11000010 Q"
1R"
0S"
b11000010 T"
0U"
0V"
0W"
LX"
b00111111 Y"
0Z"
1["
b00111111 \"
b001101001101 ]"
Z^"
Z_"
0`"
1a"
Zb"
Zc"
0d"
0e"
Zf"
Zg"
Zh"
0i"
0j"
1k"
Hl"
1m"
0n"
1o"
Zp"
0q"
1r"
Hs"
0t"
0u"
1v"
1w"
1x"
b000000 y"
b000000 z"
b11011101 {"
0|"
H}"
H!#
L"#
H##
L$#
H%#
0&#
1'#
1(#
H)#
0*#
0+#
H,#
1-#
b00110100 .#
0/#
10#
b00110100 1#
02#
03#
H4#
15#
b11011101 6#
17#
08#
b11011101 9#
b111000010001 :#
0;#
0<#
0=#
1>#
H?#
1@#
0A#
0B#
ZC#
ZD#
ZE#
1F#
ZG#
1H#
ZI#
ZJ#
0K#
1L#
HM#
1N#
1O#
HP#
1Q#
0R#
0S#
1T#
0U#
b000000 V#
b000000 W#
b00011110 X#
0Y#
0Z#
0[#
1\#
H]#
L^#
H_#
H`#
La#
1b#
Hc#
0d#
0e#
Hf#
0g#
b11100001 h#
1i#
0j#
b11100001 k#
0l#
0m#
Hn#
1o#
b00011110 p#
0q#
1r#
b00011110 s#
b111101010101 t#
0u#
0v#
0w#
1x#
Hy#
1z#
0{#
0|#
0}#
1!$
H"$
1#$
Z$$
1%$
Z&$
Z'$
0($
Z)$
Z*$
1+$
1,$
H-$
1.$
0/$
00$
11$
02$
b000000 3$
b000000 4$
b01011110 5$
06$
07$
08$
19$
0:$
1;$
H<$
H=$
L>$
L?$
H@$
0A$
0B$
HC$
0D$
b11110101 E$
1F$
0G$
b11110101 H$
0I$
0J$
HK$
1L$
b01011110 M$
0N$
1O$
b01011110 P$
b101010100001 Q$
ZR$
ZS$
0T$
1U$
HV$
ZW$
0X$
0Y$
0Z$
1[$
H\$
1]$
Z^$
1_$
Z`$
Za$
0b$
Zc$
Zd$
1e$
1f$
Hg$
1h$
0i$
0j$
Lk$
0l$
b000000 m$
b000000 n$
b00011111 o$
0p$
Hq$
Hr$
Ls$
0t$
1u$
Hv$
Hw$
Lx$
Ly$
Hz$
0{$
0|$
H}$
0!%
b10101010 "%
1#%
0$%
b10101010 %%
0&%
0'%
H(%
L)%
b00011111 *%
0+%
1,%
b00011111 -%
#20000000
0'
0.
02
06
0<
0B
0J
0T
0X
0[
1^
0n
1p
1x
0'"
0-"
01"
08"
1;"
0G"
1M"
1U"
0a"
0k"
0o"
0r"
1u"
0(#
1*#
12#
0>#
0H#
0L#
0O#
1R#
0b#
1d#
1l#
0x#
0!$
0%$
0,$
1/$
0;$
1A$
1I$
0U$
0[$
0_$
0f$
1i$
0u$
1{$
1&%
#40000000
1*
#45000000
1(
0)
1/
b000000000000000000000000000000000000000000000000000000000000000000000000000000000000000000000001 E
1K
0R
1Y
0Z
1\
0]
1_
b000001 b
b000001 c
1o
1r
1s
0u
1v
b01101000 w
1z
1}
0!"
b10011001 ""
1("
1."
19"
b000001 ?"
b000001 @"
1H"
1O"
b10000100 T"
1W"
b0111111L \"
#50000000
0(
0/
0K
0Y
0\
0o
0r
0z
0("
0."
09"
0H"
0O"
0W"
#55000000
1(
1)
1/
00
b000000000000000000000000000000000000000000000000000000000000000000000000000000000000000000000010 E
1K
0L
1R
1Y
1Z
1\
1]
0_
0`
b000010 b
b000010 c
0h
1o
1r
0s
1u
0v
b11010001 w
1z
0{
0}
1!"
b00110011 ""
1("
1."
0/"
07"
19"
0:"
1<"
b000010 ?"
b000010 @"
1H"
1O"
1P"
0R"
1S"
b00001000 T"
1W"
1Z"
0["
b111111LL \"
#60000000
0(
0/
0K
0Y
0\
0o
0r
0z
0("
0."
09"
0H"
0O"
0W"
#65000000
1(
1/
b000000000000000000000000000000000000000000000000000000000000000000000000000000000000000000000101 E
1K
1Y
1\
b000011 b
b000011 c
1o
1r
b10100010 w
1z
b01100110 ""
1("
1."
19"
b000011 ?"
b000011 @"
1H"
1O"
b00010001 T"
1W"
b11111LLL \"
#70000000
0(
0/
0K
0Y
0\
0o
0r
0z
0("
0."
09"
0H"
0O"
0W"
#75000000
1(
0)
1/
b000000000000000000000000000000000000000000000000000000000000000000000000000000000000000000001011 E
1K
0R
1Y
0Z
1\
0]
1_
b000100 b
b000100 c
1o
1r
1s
0u
1v
b01000100 w
1z
1}
0!"
b11001100 ""
1("
1."
19"
b000100 ?"
b000100 @"
1H"
1O"
b00100011 T"
1W"
b1111LLLL \"
#80000000
0(
0/
0K
0Y
0\
0o
0r
0z
0("
0."
09"
0H"
0O"
0W"
#85000000
1(
1)
1/
b000000000000000000000000000000000000000000000000000000000000000000000000000000000000000000010110 E
1K
1R
1Y
1Z
1\
1]
b000101 b
b000101 c
1o
1r
1u
0v
b10001001 w
1z
b10011000 ""
1("
1."
19"
b000101 ?"
b000101 @"
1H"
1O"
b01000111 T"
1W"
b111LLLLL \"
#90000000
0(
0/
0K
0Y
0\
0o
0r
0z
0("
0."
09"
0H"
0O"
0W"
