hardware/simulation/74hc165.vhdl
library IEEE;
use IEEE.std_logic_1164.all;

entity T74HCT165 is
port (
    nPL                 : IN  std_logic;
    nCE                : IN  std_logic;
    CP                  : IN  std_logic;
    DS                  : IN  std_logic;
    D                    : IN  std_logic_vector(7 downto 0);
    Q7                  : OUT std_logic;
    nQ7                : OUT std_logic
);
end T74HCT165;

architecture behave_T74HCT165 of T74HCT165 is
signal  Qs            : std_logic_vector(7 downto 0) ;

begin
HCT165 : process(nPL, CP, D)
begin
    if(nPL = '0') then
        Qs <= D;
    elsif(CP'event and CP = '1') then
        if(nCE = '0') then
            Qs <= Qs(6 downto 0) & DS;    -- or  Qs <= shl(Qs, '1') & DS;
        end if;
    end if;
end process;
    Q7 <= Qs(7);
    nQ7 <= not(Qs(7));
end behave_T74HCT165;

hardware/simulation/tile.vhdl
library ieee;
use ieee.std_logic_1164.all;
use IEEE.NUMERIC_STD.ALL;

entity tile is
  port (
    buttons : in std_logic_vector(11 downto 0) := (others => 'L');

    T_W : in std_logic := 'H';
    T_endcol : in std_logic := 'H';
    T_first : out std_logic := '0';
    T_latch : out std_logic;
    T_clk : out std_logic := 'L';
    T_data : in std_logic := 'L';

    B_W : out std_logic;
    B_endcol : out std_logic := '0';
    B_first : in std_logic := 'H';
    B_latch : in std_logic;
    B_clk : in std_logic;
    B_data : out std_logic;

    L_endrow : in std_logic := 'H';
    L_latch : out std_logic := 'L';
    L_clk : out std_logic := 'L';
    L_data : in std_logic := 'L';

    R_endrow : out std_logic := '0';
    R_latch : in std_logic;
    R_clk : in std_logic;
    R_data : out std_logic
  );
end tile;

architecture rtl of tile is

signal latch, clock, data : std_logic; -- sengnali principali
signal nlatch : std_logic;

signal ds_bridge : std_logic; -- sengale per connettere l'uscita seriale di SR2 a SR1
signal ds_input : std_logic; -- ds in input dai moduli adiacenti

signal w_state : std_logic; -- stato dei buffer 3state

signal count_reg : unsigned(5 downto 0) := (others => '0'); -- contatore
signal count : std_logic_vector(5 downto 0);

signal sr2_inputs : std_logic_vector(7 downto 0); -- Segnale di supporto
signal ffinput : std_logic;

begin

  nlatch <= not latch;

  -- sr LSB
  sr1 : entity work.T74HCT165
    port map(
      nPL => nlatch,
      nCE => '0',
      CP => clock,
      DS => ds_bridge,
      D => buttons(11 downto 4),
      Q7 => data,
      nQ7 => open
    );

  sr2_inputs <= buttons(3 downto 0) & "11" & L_endrow & T_endcol;

  -- sr MSB
  sr2 : entity work.T74HCT165
    port map(
      nPL => nlatch,
      nCE => '0',
      CP => clock,
      DS => ds_input,
      D => sr2_inputs,
      Q7 => ds_bridge,
      nQ7 => open
    );


  -- I/O latch clock e data
  --latch <= R_latch;
  --clock <= R_clk;
  R_data <= data;

  T_latch <= latch;
  T_clk <= clock when w_state = '0' else 'Z';

  --latch <= B_latch;
  --clock <= B_clk;
  B_data <= data;

  L_latch <= latch when w_state = '1' else 'Z';
  L_clk <= clock when w_state = '1' else 'Z';

  ds_input <= T_data when w_state = '0' else L_data;


  -- controllo di w_state
  w_state <= T_W and B_first;


  process(clock, latch)
  begin
    if latch = '1' then
      count_reg <= (others => '0');
    elsif rising_edge(clock) then
      count_reg <= count_reg + 1;
    end if;
  end process;

  count <= std_logic_vector(count_reg);
  ffinput <= count(3) and count(2) and count(1) and data; -- non mettiamo count(0) perchè col ff-sr sincrono perdiamo un ciclo

  process(clock, latch)
  begin
    if latch = '1' then
      B_W <= '0';
    elsif rising_edge(clock) then
      if ffinput = '1' then
        B_W <= '1';
      end if;
    end if;
  end process;


  -- il pezzo sotto serve solo a non far incazzare GHDL
  latch <= R_latch when to_x01(B_first) = '1' else B_latch;
  clock <= R_clk when to_x01(B_first) = '1' else B_clk;


end rtl;

hardware/simulation/tile_tb.vhdl
library ieee;
use ieee.std_logic_1164.all;
use ieee.numeric_std.all;

entity tile_tb is
end tile_tb;

architecture sim of tile_tb is

  signal buttons    : std_logic_vector(11 downto 0) := x"A53"; -- 1010 0101 0011
  signal latch, clk, data : std_logic;

  constant CLK_PERIOD : time := 10 ns;

  signal clk_en : std_logic := '0';

begin

    -- Istanza del tuo modulo
    uut: entity work.tile
        port map (
            buttons => buttons,
            T_first => open,
            T_latch => open,
            T_clk => open,
            B_W => open,
            B_endcol => open,
            B_latch => 'L',
            B_clk => 'L',
            B_data => open,
            L_latch => open,
            L_clk => open,
            R_endrow => open,
            R_latch => latch,
            R_clk => clk,
            R_data => data
        );

    -- Generatore di Clock (sulla linea R_clk)
    clk_process : process  -- RIMOSSO (clk_en)
    begin
        while now < 500 ns loop
            if clk_en = '1' then
                clk <= '0';
                wait for CLK_PERIOD/2;
                clk <= '1';
                wait for CLK_PERIOD/2;
            else
                clk <= '0';
                -- Fondamentale: se il clock è disabilitato, dobbiamo
                -- aspettare che clk_en cambi, altrimenti il loop gira
                -- all'infinito nello stesso istante di tempo (hang).
                wait until clk_en = '1';
            end if;
        end loop;
        wait; -- Ferma tutto dopo 500 ns
    end process;



    -- Stimolo principale
    stim_proc: process
    begin

        latch <= '1';  -- stato di reset
        wait for 5 ns;
        latch <= '0'; -- shifting

        clk_en <= '1';
        wait for CLK_PERIOD * 20;
        clk_en <= '0';

        wait for 20 ns;





        --wait for CLK_PERIOD * 2;
        wait;
    end process;

end sim;

hardware/simulation/tile.vcd
$date
  Thu Jan  8 01:39:06 2026
$end
$version
  GHDL v0
$end
$timescale
  1 fs
$end
$scope module standard $end
$upscope $end
$scope module std_logic_1164 $end
$upscope $end
$scope module numeric_std $end
$upscope $end
$scope module tile_tb $end
$var reg 12 ! buttons[11:0] $end
$var reg 1 " latch $end
$var reg 1 # clk $end
$var reg 1 $ data $end
$var reg 1 % clk_en $end
$scope module uut $end
$var reg 12 & buttons[11:0] $end
$var reg 1 ' t_w $end
$var reg 1 ( t_endcol $end
$var reg 1 ) t_first $end
$var reg 1 * t_latch $end
$var reg 1 + t_clk $end
$var reg 1 , t_data $end
$var reg 1 - b_w $end
$var reg 1 . b_endcol $end
$var reg 1 / b_first $end
$var reg 1 0 b_latch $end
$var reg 1 1 b_clk $end
$var reg 1 2 b_data $end
$var reg 1 3 l_endrow $end
$var reg 1 4 l_latch $end
$var reg 1 5 l_clk $end
$var reg 1 6 l_data $end
$var reg 1 7 r_endrow $end
$var reg 1 8 r_latch $end
$var reg 1 9 r_clk $end
$var reg 1 : r_data $end
$var reg 1 ; latch $end
$var reg 1 < clock $end
$var reg 1 = data $end
$var reg 1 > nlatch $end
$var reg 1 ? ds_bridge $end
$var reg 1 @ ds_input $end
$var reg 1 A w_state $end
$var reg 6 B count_reg[5:0] $end
$var reg 6 C count[5:0] $end
$var reg 8 D sr2_inputs[7:0] $end
$var reg 1 E ffinput $end
$scope module sr1 $end
$var reg 1 F npl $end
$var reg 1 G nce $end
$var reg 1 H cp $end
$var reg 1 I ds $end
$var reg 8 J d[7:0] $end
$var reg 1 K q7 $end
$var reg 1 L nq7 $end
$var reg 8 M qs[7:0] $end
$upscope $end
$scope module sr2 $end
$var reg 1 N npl $end
$var reg 1 O nce $end
$var reg 1 P cp $end
$var reg 1 Q ds $end
$var reg 8 R d[7:0] $end
$var reg 1 S q7 $end
$var reg 1 T nq7 $end
$var reg 8 U qs[7:0] $end
$upscope $end
$upscope $end
$upscope $end
$enddefinitions $end
#0
b101001010011 !
1"
0#
1$
0%
b101001010011 &
H'
H(
0)
1*
Z+
L,
0-
0.
H/
L0
L1
12
H3
14
05
L6
07
18
09
1:
1;
0<
1=
0>
0?
L@
1A
b000000 B
b000000 C
b001111HH D
0E
0F
0G
0H
0I
b10100101 J
1K
0L
b10100101 M
0N
0O
0P
LQ
b001111HH R
0S
1T
b001111HH U
#5000000
0"
1%
0*
04
08
0;
1>
1F
1N
#10000000
1#
0$
02
15
19
0:
1<
0=
b000001 B
b000001 C
1H
0K
1L
b01001010 M
1P
b01111HHL U
#15000000
0#
05
09
0<
0H
0P
#20000000
1#
1$
12
15
19
1:
1<
1=
1?
b000010 B
b000010 C
1H
1I
1K
0L
b10010100 M
1P
1S
0T
b1111HHLL U
#25000000
0#
05
09
0<
0H
0P
#30000000
1#
0$
02
15
19
0:
1<
0=
b000011 B
b000011 C
1H
0K
1L
b00101001 M
1P
b111HHLLL U
#35000000
0#
05
09
0<
0H
0P
#40000000
1#
15
19
1<
b000100 B
b000100 C
1H
b01010011 M
1P
b11HHLLLL U
#45000000
0#
05
09
0<
0H
0P
#50000000
1#
1$
12
15
19
1:
1<
1=
b000101 B
b000101 C
1H
1K
0L
b10100111 M
1P
b1HHLLLLL U
#55000000
0#
05
09
0<
0H
0P
#60000000
1#
0$
02
15
19
0:
1<
0=
H?
b000110 B
b000110 C
1H
HI
0K
1L
b01001111 M
1P
HS
bHHLLLLLL U
#65000000
0#
05
09
0<
0H
0P
#70000000
1#
1$
12
15
19
1:
1<
1=
b000111 B
b000111 C
1H
1K
0L
b1001111H M
1P
bHLLLLLLL U
#75000000
0#
05
09
0<
0H
0P
#80000000
1#
0$
02
15
19
0:
1<
0=
L?
b001000 B
b001000 C
1H
LI
0K
1L
b001111HH M
1P
LS
1T
bLLLLLLLL U
#85000000
0#
05
09
0<
0H
0P
#90000000
1#
15
19
1<
b001001 B
b001001 C
1H
b01111HHL M
1P
#95000000
0#
05
09
0<
0H
0P
#100000000
1#
1$
12
15
19
1:
1<
1=
b001010 B
b001010 C
1H
1K
0L
b1111HHLL M
1P
#105000000
0#
05
09
0<
0H
0P
#110000000
1#
15
19
1<
b001011 B
b001011 C
1H
b111HHLLL M
1P
#115000000
0#
05
09
0<
0H
0P
#120000000
1#
15
19
1<
b001100 B
b001100 C
1H
b11HHLLLL M
1P
#125000000
0#
05
09
0<
0H
0P
#130000000
1#
15
19
1<
b001101 B
b001101 C
1H
b1HHLLLLL M
1P
#135000000
0#
05
09
0<
0H
0P
#140000000
1#
H$
H2
15
19
H:
1<
H=
b001110 B
b001110 C
1E
1H
HK
bHHLLLLLL M
1P
#145000000
0#
05
09
0<
0H
0P
#150000000
1#
1-
15
19
1<
b001111 B
b001111 C
1H
bHLLLLLLL M
1P
#155000000
0#
05
09
0<
0H
0P
#160000000
1#
L$
L2
15
19
L:
1<
L=
b010000 B
b010000 C
0E
1H
LK
1L
bLLLLLLLL M
1P
#165000000
0#
05
09
0<
0H
0P
#170000000
1#
15
19
1<
b010001 B
b010001 C
1H
1P
#175000000
0#
05
09
0<
0H
0P
#180000000
1#
15
19
1<
b010010 B
b010010 C
1H
1P
#185000000
0#
05
09
0<
0H
0P
#190000000
1#
15
19
1<
b010011 B
b010011 C
1H
1P
#195000000
0#
05
09
0<
0H
0P
#200000000
1#
15
19
1<
b010100 B
b010100 C
1H
1P
#205000000
0#
0%
05
09
0<
0H
0P
#210000000
1#
15
19
1<
b010101 B
b010101 C
1H
1P
#215000000
0#
05
09
0<
0H
0P
